[{"block":214001,"size":0,"storage":
[]},
{"block":214002,"size":0,"storage":
[]},
{"block":214003,"size":0,"storage":
[]},
{"block":214004,"size":0,"storage":
[]},
{"block":214005,"size":0,"storage":
[]},
{"block":214006,"size":0,"storage":
[]},
{"block":214007,"size":0,"storage":
[]},
{"block":214008,"size":0,"storage":
[]},
{"block":214009,"size":0,"storage":
[]},
{"block":214010,"size":0,"storage":
[]},
{"block":214011,"size":0,"storage":
[]},
{"block":214012,"size":0,"storage":
[]},
{"block":214013,"size":0,"storage":
[]},
{"block":214014,"size":0,"storage":
[]},
{"block":214015,"size":0,"storage":
[]},
{"block":214016,"size":0,"storage":
[]},
{"block":214017,"size":0,"storage":
[]},
{"block":214018,"size":0,"storage":
[]},
{"block":214019,"size":0,"storage":
[]},
{"block":214020,"size":0,"storage":
[]},
{"block":214021,"size":0,"storage":
[]},
{"block":214022,"size":0,"storage":
[]},
{"block":214023,"size":0,"storage":
[]},
{"block":214024,"size":0,"storage":
[]},
{"block":214025,"size":0,"storage":
[]},
{"block":214026,"size":0,"storage":
[]},
{"block":214027,"size":0,"storage":
[]},
{"block":214028,"size":0,"storage":
[]},
{"block":214029,"size":0,"storage":
[]},
{"block":214030,"size":0,"storage":
[]},
{"block":214031,"size":0,"storage":
[]},
{"block":214032,"size":0,"storage":
[]},
{"block":214033,"size":0,"storage":
[]},
{"block":214034,"size":0,"storage":
[]},
{"block":214035,"size":0,"storage":
[]},
{"block":214036,"size":0,"storage":
[]},
{"block":214037,"size":0,"storage":
[]},
{"block":214038,"size":0,"storage":
[]},
{"block":214039,"size":0,"storage":
[]},
{"block":214040,"size":0,"storage":
[]},
{"block":214041,"size":0,"storage":
[]},
{"block":214042,"size":0,"storage":
[]},
{"block":214043,"size":0,"storage":
[]},
{"block":214044,"size":0,"storage":
[]},
{"block":214045,"size":0,"storage":
[]},
{"block":214046,"size":0,"storage":
[]},
{"block":214047,"size":0,"storage":
[]},
{"block":214048,"size":0,"storage":
[]},
{"block":214049,"size":0,"storage":
[]},
{"block":214050,"size":0,"storage":
[]},
{"block":214051,"size":0,"storage":
[]},
{"block":214052,"size":0,"storage":
[]},
{"block":214053,"size":0,"storage":
[]},
{"block":214054,"size":0,"storage":
[]},
{"block":214055,"size":0,"storage":
[]},
{"block":214056,"size":0,"storage":
[]},
{"block":214057,"size":0,"storage":
[]},
{"block":214058,"size":0,"storage":
[]},
{"block":214059,"size":0,"storage":
[]},
{"block":214060,"size":0,"storage":
[]},
{"block":214061,"size":0,"storage":
[]},
{"block":214062,"size":0,"storage":
[]},
{"block":214063,"size":0,"storage":
[]},
{"block":214064,"size":0,"storage":
[]},
{"block":214065,"size":0,"storage":
[]},
{"block":214066,"size":0,"storage":
[]},
{"block":214067,"size":0,"storage":
[]},
{"block":214068,"size":0,"storage":
[]},
{"block":214069,"size":0,"storage":
[]},
{"block":214070,"size":0,"storage":
[]},
{"block":214071,"size":0,"storage":
[]},
{"block":214072,"size":0,"storage":
[]},
{"block":214073,"size":0,"storage":
[]},
{"block":214074,"size":0,"storage":
[]},
{"block":214075,"size":0,"storage":
[]},
{"block":214076,"size":0,"storage":
[]},
{"block":214077,"size":0,"storage":
[]},
{"block":214078,"size":0,"storage":
[]},
{"block":214079,"size":0,"storage":
[]},
{"block":214080,"size":0,"storage":
[]},
{"block":214081,"size":0,"storage":
[]},
{"block":214082,"size":0,"storage":
[]},
{"block":214083,"size":0,"storage":
[]},
{"block":214084,"size":0,"storage":
[]},
{"block":214085,"size":0,"storage":
[]},
{"block":214086,"size":0,"storage":
[]},
{"block":214087,"size":0,"storage":
[]},
{"block":214088,"size":0,"storage":
[]},
{"block":214089,"size":0,"storage":
[]},
{"block":214090,"size":0,"storage":
[]},
{"block":214091,"size":0,"storage":
[]},
{"block":214092,"size":0,"storage":
[]},
{"block":214093,"size":0,"storage":
[]},
{"block":214094,"size":0,"storage":
[]},
{"block":214095,"size":0,"storage":
[]},
{"block":214096,"size":0,"storage":
[]},
{"block":214097,"size":0,"storage":
[]},
{"block":214098,"size":0,"storage":
[]},
{"block":214099,"size":0,"storage":
[]},
{"block":214100,"size":0,"storage":
[]},
{"block":214101,"size":0,"storage":
[]},
{"block":214102,"size":0,"storage":
[]},
{"block":214103,"size":0,"storage":
[]},
{"block":214104,"size":0,"storage":
[]},
{"block":214105,"size":0,"storage":
[]},
{"block":214106,"size":0,"storage":
[]},
{"block":214107,"size":0,"storage":
[]},
{"block":214108,"size":0,"storage":
[]},
{"block":214109,"size":0,"storage":
[]},
{"block":214110,"size":0,"storage":
[]},
{"block":214111,"size":0,"storage":
[]},
{"block":214112,"size":0,"storage":
[]},
{"block":214113,"size":0,"storage":
[]},
{"block":214114,"size":0,"storage":
[]},
{"block":214115,"size":0,"storage":
[]},
{"block":214116,"size":0,"storage":
[]},
{"block":214117,"size":0,"storage":
[]},
{"block":214118,"size":0,"storage":
[]},
{"block":214119,"size":0,"storage":
[]},
{"block":214120,"size":0,"storage":
[]},
{"block":214121,"size":0,"storage":
[]},
{"block":214122,"size":0,"storage":
[]},
{"block":214123,"size":0,"storage":
[]},
{"block":214124,"size":0,"storage":
[]},
{"block":214125,"size":0,"storage":
[]},
{"block":214126,"size":0,"storage":
[]},
{"block":214127,"size":0,"storage":
[]},
{"block":214128,"size":0,"storage":
[]},
{"block":214129,"size":0,"storage":
[]},
{"block":214130,"size":0,"storage":
[]},
{"block":214131,"size":0,"storage":
[]},
{"block":214132,"size":0,"storage":
[]},
{"block":214133,"size":0,"storage":
[]},
{"block":214134,"size":0,"storage":
[]},
{"block":214135,"size":0,"storage":
[]},
{"block":214136,"size":0,"storage":
[]},
{"block":214137,"size":0,"storage":
[]},
{"block":214138,"size":0,"storage":
[]},
{"block":214139,"size":0,"storage":
[]},
{"block":214140,"size":0,"storage":
[]},
{"block":214141,"size":0,"storage":
[]},
{"block":214142,"size":0,"storage":
[]},
{"block":214143,"size":0,"storage":
[]},
{"block":214144,"size":0,"storage":
[]},
{"block":214145,"size":0,"storage":
[]},
{"block":214146,"size":0,"storage":
[]},
{"block":214147,"size":0,"storage":
[]},
{"block":214148,"size":0,"storage":
[]},
{"block":214149,"size":0,"storage":
[]},
{"block":214150,"size":0,"storage":
[]},
{"block":214151,"size":0,"storage":
[]},
{"block":214152,"size":0,"storage":
[]},
{"block":214153,"size":0,"storage":
[]},
{"block":214154,"size":0,"storage":
[]},
{"block":214155,"size":0,"storage":
[]},
{"block":214156,"size":0,"storage":
[]},
{"block":214157,"size":0,"storage":
[]},
{"block":214158,"size":0,"storage":
[]},
{"block":214159,"size":0,"storage":
[]},
{"block":214160,"size":0,"storage":
[]},
{"block":214161,"size":0,"storage":
[]},
{"block":214162,"size":0,"storage":
[]},
{"block":214163,"size":0,"storage":
[]},
{"block":214164,"size":0,"storage":
[]},
{"block":214165,"size":0,"storage":
[]},
{"block":214166,"size":0,"storage":
[]},
{"block":214167,"size":0,"storage":
[]},
{"block":214168,"size":0,"storage":
[]},
{"block":214169,"size":0,"storage":
[]},
{"block":214170,"size":0,"storage":
[]},
{"block":214171,"size":0,"storage":
[]},
{"block":214172,"size":0,"storage":
[]},
{"block":214173,"size":0,"storage":
[]},
{"block":214174,"size":0,"storage":
[]},
{"block":214175,"size":0,"storage":
[]},
{"block":214176,"size":0,"storage":
[]},
{"block":214177,"size":0,"storage":
[]},
{"block":214178,"size":0,"storage":
[]},
{"block":214179,"size":0,"storage":
[]},
{"block":214180,"size":0,"storage":
[]},
{"block":214181,"size":0,"storage":
[]},
{"block":214182,"size":0,"storage":
[]},
{"block":214183,"size":0,"storage":
[]},
{"block":214184,"size":0,"storage":
[]},
{"block":214185,"size":0,"storage":
[]},
{"block":214186,"size":0,"storage":
[]},
{"block":214187,"size":0,"storage":
[]},
{"block":214188,"size":0,"storage":
[]},
{"block":214189,"size":0,"storage":
[]},
{"block":214190,"size":0,"storage":
[]},
{"block":214191,"size":0,"storage":
[]},
{"block":214192,"size":0,"storage":
[]},
{"block":214193,"size":0,"storage":
[]},
{"block":214194,"size":0,"storage":
[]},
{"block":214195,"size":0,"storage":
[]},
{"block":214196,"size":0,"storage":
[]},
{"block":214197,"size":0,"storage":
[]},
{"block":214198,"size":0,"storage":
[]},
{"block":214199,"size":0,"storage":
[]},
{"block":214200,"size":0,"storage":
[]},
{"block":214201,"size":0,"storage":
[]},
{"block":214202,"size":0,"storage":
[]},
{"block":214203,"size":0,"storage":
[]},
{"block":214204,"size":0,"storage":
[]},
{"block":214205,"size":0,"storage":
[]},
{"block":214206,"size":0,"storage":
[]},
{"block":214207,"size":0,"storage":
[]},
{"block":214208,"size":0,"storage":
[]},
{"block":214209,"size":0,"storage":
[]},
{"block":214210,"size":0,"storage":
[]},
{"block":214211,"size":0,"storage":
[]},
{"block":214212,"size":0,"storage":
[]},
{"block":214213,"size":0,"storage":
[]},
{"block":214214,"size":0,"storage":
[]},
{"block":214215,"size":0,"storage":
[]},
{"block":214216,"size":0,"storage":
[]},
{"block":214217,"size":0,"storage":
[]},
{"block":214218,"size":0,"storage":
[]},
{"block":214219,"size":0,"storage":
[]},
{"block":214220,"size":0,"storage":
[]},
{"block":214221,"size":0,"storage":
[]},
{"block":214222,"size":0,"storage":
[]},
{"block":214223,"size":0,"storage":
[]},
{"block":214224,"size":0,"storage":
[]},
{"block":214225,"size":0,"storage":
[]},
{"block":214226,"size":0,"storage":
[]},
{"block":214227,"size":0,"storage":
[]},
{"block":214228,"size":0,"storage":
[]},
{"block":214229,"size":0,"storage":
[]},
{"block":214230,"size":0,"storage":
[]},
{"block":214231,"size":0,"storage":
[]},
{"block":214232,"size":0,"storage":
[]},
{"block":214233,"size":0,"storage":
[]},
{"block":214234,"size":0,"storage":
[]},
{"block":214235,"size":0,"storage":
[]},
{"block":214236,"size":0,"storage":
[]},
{"block":214237,"size":0,"storage":
[]},
{"block":214238,"size":0,"storage":
[]},
{"block":214239,"size":0,"storage":
[]},
{"block":214240,"size":0,"storage":
[]},
{"block":214241,"size":0,"storage":
[]},
{"block":214242,"size":0,"storage":
[]},
{"block":214243,"size":0,"storage":
[]},
{"block":214244,"size":0,"storage":
[]},
{"block":214245,"size":0,"storage":
[]},
{"block":214246,"size":0,"storage":
[]},
{"block":214247,"size":0,"storage":
[]},
{"block":214248,"size":0,"storage":
[]},
{"block":214249,"size":0,"storage":
[]},
{"block":214250,"size":0,"storage":
[]},
{"block":214251,"size":0,"storage":
[]},
{"block":214252,"size":0,"storage":
[]},
{"block":214253,"size":0,"storage":
[]},
{"block":214254,"size":0,"storage":
[]},
{"block":214255,"size":0,"storage":
[]},
{"block":214256,"size":0,"storage":
[]},
{"block":214257,"size":0,"storage":
[]},
{"block":214258,"size":0,"storage":
[]},
{"block":214259,"size":0,"storage":
[]},
{"block":214260,"size":0,"storage":
[]},
{"block":214261,"size":0,"storage":
[]},
{"block":214262,"size":0,"storage":
[]},
{"block":214263,"size":0,"storage":
[]},
{"block":214264,"size":0,"storage":
[]},
{"block":214265,"size":0,"storage":
[]},
{"block":214266,"size":0,"storage":
[]},
{"block":214267,"size":0,"storage":
[]},
{"block":214268,"size":0,"storage":
[]},
{"block":214269,"size":0,"storage":
[]},
{"block":214270,"size":0,"storage":
[]},
{"block":214271,"size":0,"storage":
[]},
{"block":214272,"size":0,"storage":
[]},
{"block":214273,"size":0,"storage":
[]},
{"block":214274,"size":0,"storage":
[]},
{"block":214275,"size":0,"storage":
[]},
{"block":214276,"size":0,"storage":
[]},
{"block":214277,"size":0,"storage":
[]},
{"block":214278,"size":0,"storage":
[]},
{"block":214279,"size":0,"storage":
[]},
{"block":214280,"size":0,"storage":
[]},
{"block":214281,"size":0,"storage":
[]},
{"block":214282,"size":0,"storage":
[]},
{"block":214283,"size":0,"storage":
[]},
{"block":214284,"size":0,"storage":
[]},
{"block":214285,"size":0,"storage":
[]},
{"block":214286,"size":0,"storage":
[]},
{"block":214287,"size":0,"storage":
[]},
{"block":214288,"size":0,"storage":
[]},
{"block":214289,"size":0,"storage":
[]},
{"block":214290,"size":0,"storage":
[]},
{"block":214291,"size":0,"storage":
[]},
{"block":214292,"size":0,"storage":
[]},
{"block":214293,"size":0,"storage":
[]},
{"block":214294,"size":0,"storage":
[]},
{"block":214295,"size":0,"storage":
[]},
{"block":214296,"size":0,"storage":
[]},
{"block":214297,"size":0,"storage":
[]},
{"block":214298,"size":0,"storage":
[]},
{"block":214299,"size":0,"storage":
[]},
{"block":214300,"size":0,"storage":
[]},
{"block":214301,"size":0,"storage":
[]},
{"block":214302,"size":0,"storage":
[]},
{"block":214303,"size":0,"storage":
[]},
{"block":214304,"size":0,"storage":
[]},
{"block":214305,"size":0,"storage":
[]},
{"block":214306,"size":0,"storage":
[]},
{"block":214307,"size":0,"storage":
[]},
{"block":214308,"size":0,"storage":
[]},
{"block":214309,"size":0,"storage":
[]},
{"block":214310,"size":0,"storage":
[]},
{"block":214311,"size":0,"storage":
[]},
{"block":214312,"size":0,"storage":
[]},
{"block":214313,"size":0,"storage":
[]},
{"block":214314,"size":0,"storage":
[]},
{"block":214315,"size":0,"storage":
[]},
{"block":214316,"size":0,"storage":
[]},
{"block":214317,"size":0,"storage":
[]},
{"block":214318,"size":0,"storage":
[]},
{"block":214319,"size":0,"storage":
[]},
{"block":214320,"size":0,"storage":
[]},
{"block":214321,"size":0,"storage":
[]},
{"block":214322,"size":0,"storage":
[]},
{"block":214323,"size":0,"storage":
[]},
{"block":214324,"size":0,"storage":
[]},
{"block":214325,"size":0,"storage":
[]},
{"block":214326,"size":0,"storage":
[]},
{"block":214327,"size":0,"storage":
[]},
{"block":214328,"size":0,"storage":
[]},
{"block":214329,"size":0,"storage":
[]},
{"block":214330,"size":0,"storage":
[]},
{"block":214331,"size":0,"storage":
[]},
{"block":214332,"size":0,"storage":
[]},
{"block":214333,"size":0,"storage":
[]},
{"block":214334,"size":0,"storage":
[]},
{"block":214335,"size":0,"storage":
[]},
{"block":214336,"size":0,"storage":
[]},
{"block":214337,"size":0,"storage":
[]},
{"block":214338,"size":0,"storage":
[]},
{"block":214339,"size":0,"storage":
[]},
{"block":214340,"size":0,"storage":
[]},
{"block":214341,"size":0,"storage":
[]},
{"block":214342,"size":0,"storage":
[]},
{"block":214343,"size":0,"storage":
[]},
{"block":214344,"size":0,"storage":
[]},
{"block":214345,"size":0,"storage":
[]},
{"block":214346,"size":0,"storage":
[]},
{"block":214347,"size":0,"storage":
[]},
{"block":214348,"size":0,"storage":
[]},
{"block":214349,"size":0,"storage":
[]},
{"block":214350,"size":0,"storage":
[]},
{"block":214351,"size":0,"storage":
[]},
{"block":214352,"size":0,"storage":
[]},
{"block":214353,"size":0,"storage":
[]},
{"block":214354,"size":0,"storage":
[]},
{"block":214355,"size":0,"storage":
[]},
{"block":214356,"size":0,"storage":
[]},
{"block":214357,"size":0,"storage":
[]},
{"block":214358,"size":0,"storage":
[]},
{"block":214359,"size":0,"storage":
[]},
{"block":214360,"size":0,"storage":
[]},
{"block":214361,"size":0,"storage":
[]},
{"block":214362,"size":0,"storage":
[]},
{"block":214363,"size":0,"storage":
[]},
{"block":214364,"size":0,"storage":
[]},
{"block":214365,"size":0,"storage":
[]},
{"block":214366,"size":0,"storage":
[]},
{"block":214367,"size":0,"storage":
[]},
{"block":214368,"size":0,"storage":
[]},
{"block":214369,"size":0,"storage":
[]},
{"block":214370,"size":0,"storage":
[]},
{"block":214371,"size":0,"storage":
[]},
{"block":214372,"size":0,"storage":
[]},
{"block":214373,"size":0,"storage":
[]},
{"block":214374,"size":0,"storage":
[]},
{"block":214375,"size":0,"storage":
[]},
{"block":214376,"size":0,"storage":
[]},
{"block":214377,"size":0,"storage":
[]},
{"block":214378,"size":0,"storage":
[]},
{"block":214379,"size":0,"storage":
[]},
{"block":214380,"size":0,"storage":
[]},
{"block":214381,"size":0,"storage":
[]},
{"block":214382,"size":0,"storage":
[]},
{"block":214383,"size":0,"storage":
[]},
{"block":214384,"size":0,"storage":
[]},
{"block":214385,"size":0,"storage":
[]},
{"block":214386,"size":0,"storage":
[]},
{"block":214387,"size":0,"storage":
[]},
{"block":214388,"size":0,"storage":
[]},
{"block":214389,"size":0,"storage":
[]},
{"block":214390,"size":0,"storage":
[]},
{"block":214391,"size":0,"storage":
[]},
{"block":214392,"size":0,"storage":
[]},
{"block":214393,"size":0,"storage":
[]},
{"block":214394,"size":0,"storage":
[]},
{"block":214395,"size":0,"storage":
[]},
{"block":214396,"size":0,"storage":
[]},
{"block":214397,"size":0,"storage":
[]},
{"block":214398,"size":0,"storage":
[]},
{"block":214399,"size":0,"storage":
[]},
{"block":214400,"size":0,"storage":
[]},
{"block":214401,"size":0,"storage":
[]},
{"block":214402,"size":0,"storage":
[]},
{"block":214403,"size":0,"storage":
[]},
{"block":214404,"size":0,"storage":
[]},
{"block":214405,"size":0,"storage":
[]},
{"block":214406,"size":0,"storage":
[]},
{"block":214407,"size":0,"storage":
[]},
{"block":214408,"size":0,"storage":
[]},
{"block":214409,"size":0,"storage":
[]},
{"block":214410,"size":0,"storage":
[]},
{"block":214411,"size":0,"storage":
[]},
{"block":214412,"size":0,"storage":
[]},
{"block":214413,"size":0,"storage":
[]},
{"block":214414,"size":0,"storage":
[]},
{"block":214415,"size":0,"storage":
[]},
{"block":214416,"size":0,"storage":
[]},
{"block":214417,"size":0,"storage":
[]},
{"block":214418,"size":0,"storage":
[]},
{"block":214419,"size":0,"storage":
[]},
{"block":214420,"size":0,"storage":
[]},
{"block":214421,"size":0,"storage":
[]},
{"block":214422,"size":0,"storage":
[]},
{"block":214423,"size":0,"storage":
[]},
{"block":214424,"size":0,"storage":
[]},
{"block":214425,"size":0,"storage":
[]},
{"block":214426,"size":0,"storage":
[]},
{"block":214427,"size":0,"storage":
[]},
{"block":214428,"size":0,"storage":
[]},
{"block":214429,"size":0,"storage":
[]},
{"block":214430,"size":0,"storage":
[]},
{"block":214431,"size":0,"storage":
[]},
{"block":214432,"size":0,"storage":
[]},
{"block":214433,"size":0,"storage":
[]},
{"block":214434,"size":0,"storage":
[]},
{"block":214435,"size":0,"storage":
[]},
{"block":214436,"size":0,"storage":
[]},
{"block":214437,"size":0,"storage":
[]},
{"block":214438,"size":0,"storage":
[]},
{"block":214439,"size":0,"storage":
[]},
{"block":214440,"size":0,"storage":
[]},
{"block":214441,"size":0,"storage":
[]},
{"block":214442,"size":0,"storage":
[]},
{"block":214443,"size":0,"storage":
[]},
{"block":214444,"size":0,"storage":
[]},
{"block":214445,"size":0,"storage":
[]},
{"block":214446,"size":0,"storage":
[]},
{"block":214447,"size":0,"storage":
[]},
{"block":214448,"size":0,"storage":
[]},
{"block":214449,"size":0,"storage":
[]},
{"block":214450,"size":0,"storage":
[]},
{"block":214451,"size":0,"storage":
[]},
{"block":214452,"size":0,"storage":
[]},
{"block":214453,"size":0,"storage":
[]},
{"block":214454,"size":0,"storage":
[]},
{"block":214455,"size":0,"storage":
[]},
{"block":214456,"size":0,"storage":
[]},
{"block":214457,"size":0,"storage":
[]},
{"block":214458,"size":0,"storage":
[]},
{"block":214459,"size":0,"storage":
[]},
{"block":214460,"size":0,"storage":
[]},
{"block":214461,"size":0,"storage":
[]},
{"block":214462,"size":0,"storage":
[]},
{"block":214463,"size":0,"storage":
[]},
{"block":214464,"size":0,"storage":
[]},
{"block":214465,"size":0,"storage":
[]},
{"block":214466,"size":0,"storage":
[]},
{"block":214467,"size":0,"storage":
[]},
{"block":214468,"size":0,"storage":
[]},
{"block":214469,"size":0,"storage":
[]},
{"block":214470,"size":0,"storage":
[]},
{"block":214471,"size":0,"storage":
[]},
{"block":214472,"size":0,"storage":
[]},
{"block":214473,"size":0,"storage":
[]},
{"block":214474,"size":0,"storage":
[]},
{"block":214475,"size":0,"storage":
[]},
{"block":214476,"size":0,"storage":
[]},
{"block":214477,"size":0,"storage":
[]},
{"block":214478,"size":0,"storage":
[]},
{"block":214479,"size":0,"storage":
[]},
{"block":214480,"size":0,"storage":
[]},
{"block":214481,"size":0,"storage":
[]},
{"block":214482,"size":0,"storage":
[]},
{"block":214483,"size":0,"storage":
[]},
{"block":214484,"size":0,"storage":
[]},
{"block":214485,"size":0,"storage":
[]},
{"block":214486,"size":0,"storage":
[]},
{"block":214487,"size":0,"storage":
[]},
{"block":214488,"size":0,"storage":
[]},
{"block":214489,"size":0,"storage":
[]},
{"block":214490,"size":0,"storage":
[]},
{"block":214491,"size":0,"storage":
[]},
{"block":214492,"size":0,"storage":
[]},
{"block":214493,"size":0,"storage":
[]},
{"block":214494,"size":0,"storage":
[]},
{"block":214495,"size":0,"storage":
[]},
{"block":214496,"size":0,"storage":
[]},
{"block":214497,"size":0,"storage":
[]},
{"block":214498,"size":0,"storage":
[]},
{"block":214499,"size":0,"storage":
[]},
{"block":214500,"size":0,"storage":
[]},
{"block":214501,"size":0,"storage":
[]},
{"block":214502,"size":0,"storage":
[]},
{"block":214503,"size":0,"storage":
[]},
{"block":214504,"size":0,"storage":
[]},
{"block":214505,"size":0,"storage":
[]},
{"block":214506,"size":0,"storage":
[]},
{"block":214507,"size":0,"storage":
[]},
{"block":214508,"size":0,"storage":
[]},
{"block":214509,"size":0,"storage":
[]},
{"block":214510,"size":0,"storage":
[]},
{"block":214511,"size":0,"storage":
[]},
{"block":214512,"size":0,"storage":
[]},
{"block":214513,"size":0,"storage":
[]},
{"block":214514,"size":0,"storage":
[]},
{"block":214515,"size":0,"storage":
[]},
{"block":214516,"size":0,"storage":
[]},
{"block":214517,"size":0,"storage":
[]},
{"block":214518,"size":0,"storage":
[]},
{"block":214519,"size":0,"storage":
[]},
{"block":214520,"size":0,"storage":
[]},
{"block":214521,"size":0,"storage":
[]},
{"block":214522,"size":0,"storage":
[]},
{"block":214523,"size":0,"storage":
[]},
{"block":214524,"size":0,"storage":
[]},
{"block":214525,"size":0,"storage":
[]},
{"block":214526,"size":0,"storage":
[]},
{"block":214527,"size":0,"storage":
[]},
{"block":214528,"size":0,"storage":
[]},
{"block":214529,"size":0,"storage":
[]},
{"block":214530,"size":0,"storage":
[]},
{"block":214531,"size":0,"storage":
[]},
{"block":214532,"size":0,"storage":
[]},
{"block":214533,"size":0,"storage":
[]},
{"block":214534,"size":0,"storage":
[]},
{"block":214535,"size":0,"storage":
[]},
{"block":214536,"size":0,"storage":
[]},
{"block":214537,"size":0,"storage":
[]},
{"block":214538,"size":0,"storage":
[]},
{"block":214539,"size":0,"storage":
[]},
{"block":214540,"size":0,"storage":
[]},
{"block":214541,"size":0,"storage":
[]},
{"block":214542,"size":0,"storage":
[]},
{"block":214543,"size":0,"storage":
[]},
{"block":214544,"size":0,"storage":
[]},
{"block":214545,"size":0,"storage":
[]},
{"block":214546,"size":0,"storage":
[]},
{"block":214547,"size":0,"storage":
[]},
{"block":214548,"size":0,"storage":
[]},
{"block":214549,"size":0,"storage":
[]},
{"block":214550,"size":0,"storage":
[]},
{"block":214551,"size":0,"storage":
[]},
{"block":214552,"size":0,"storage":
[]},
{"block":214553,"size":0,"storage":
[]},
{"block":214554,"size":0,"storage":
[]},
{"block":214555,"size":0,"storage":
[]},
{"block":214556,"size":0,"storage":
[]},
{"block":214557,"size":0,"storage":
[]},
{"block":214558,"size":0,"storage":
[]},
{"block":214559,"size":0,"storage":
[]},
{"block":214560,"size":0,"storage":
[]},
{"block":214561,"size":0,"storage":
[]},
{"block":214562,"size":0,"storage":
[]},
{"block":214563,"size":0,"storage":
[]},
{"block":214564,"size":0,"storage":
[]},
{"block":214565,"size":0,"storage":
[]},
{"block":214566,"size":0,"storage":
[]},
{"block":214567,"size":0,"storage":
[]},
{"block":214568,"size":0,"storage":
[]},
{"block":214569,"size":0,"storage":
[]},
{"block":214570,"size":0,"storage":
[]},
{"block":214571,"size":0,"storage":
[]},
{"block":214572,"size":0,"storage":
[]},
{"block":214573,"size":0,"storage":
[]},
{"block":214574,"size":0,"storage":
[]},
{"block":214575,"size":0,"storage":
[]},
{"block":214576,"size":0,"storage":
[]},
{"block":214577,"size":0,"storage":
[]},
{"block":214578,"size":0,"storage":
[]},
{"block":214579,"size":0,"storage":
[]},
{"block":214580,"size":0,"storage":
[]},
{"block":214581,"size":0,"storage":
[]},
{"block":214582,"size":0,"storage":
[]},
{"block":214583,"size":0,"storage":
[]},
{"block":214584,"size":0,"storage":
[]},
{"block":214585,"size":0,"storage":
[]},
{"block":214586,"size":0,"storage":
[]},
{"block":214587,"size":0,"storage":
[]},
{"block":214588,"size":0,"storage":
[]},
{"block":214589,"size":0,"storage":
[]},
{"block":214590,"size":0,"storage":
[]},
{"block":214591,"size":0,"storage":
[]},
{"block":214592,"size":0,"storage":
[]},
{"block":214593,"size":0,"storage":
[]},
{"block":214594,"size":0,"storage":
[]},
{"block":214595,"size":0,"storage":
[]},
{"block":214596,"size":0,"storage":
[]},
{"block":214597,"size":0,"storage":
[]},
{"block":214598,"size":0,"storage":
[]},
{"block":214599,"size":0,"storage":
[]},
{"block":214600,"size":0,"storage":
[]},
{"block":214601,"size":0,"storage":
[]},
{"block":214602,"size":0,"storage":
[]},
{"block":214603,"size":0,"storage":
[]},
{"block":214604,"size":0,"storage":
[]},
{"block":214605,"size":0,"storage":
[]},
{"block":214606,"size":0,"storage":
[]},
{"block":214607,"size":0,"storage":
[]},
{"block":214608,"size":0,"storage":
[]},
{"block":214609,"size":0,"storage":
[]},
{"block":214610,"size":0,"storage":
[]},
{"block":214611,"size":0,"storage":
[]},
{"block":214612,"size":0,"storage":
[]},
{"block":214613,"size":0,"storage":
[]},
{"block":214614,"size":0,"storage":
[]},
{"block":214615,"size":0,"storage":
[]},
{"block":214616,"size":0,"storage":
[]},
{"block":214617,"size":0,"storage":
[]},
{"block":214618,"size":0,"storage":
[]},
{"block":214619,"size":0,"storage":
[]},
{"block":214620,"size":0,"storage":
[]},
{"block":214621,"size":0,"storage":
[]},
{"block":214622,"size":0,"storage":
[]},
{"block":214623,"size":0,"storage":
[]},
{"block":214624,"size":0,"storage":
[]},
{"block":214625,"size":0,"storage":
[]},
{"block":214626,"size":0,"storage":
[]},
{"block":214627,"size":0,"storage":
[]},
{"block":214628,"size":0,"storage":
[]},
{"block":214629,"size":0,"storage":
[]},
{"block":214630,"size":0,"storage":
[]},
{"block":214631,"size":0,"storage":
[]},
{"block":214632,"size":0,"storage":
[]},
{"block":214633,"size":0,"storage":
[]},
{"block":214634,"size":0,"storage":
[]},
{"block":214635,"size":0,"storage":
[]},
{"block":214636,"size":0,"storage":
[]},
{"block":214637,"size":0,"storage":
[]},
{"block":214638,"size":0,"storage":
[]},
{"block":214639,"size":0,"storage":
[]},
{"block":214640,"size":0,"storage":
[]},
{"block":214641,"size":0,"storage":
[]},
{"block":214642,"size":0,"storage":
[]},
{"block":214643,"size":0,"storage":
[]},
{"block":214644,"size":0,"storage":
[]},
{"block":214645,"size":0,"storage":
[]},
{"block":214646,"size":0,"storage":
[]},
{"block":214647,"size":0,"storage":
[]},
{"block":214648,"size":0,"storage":
[]},
{"block":214649,"size":0,"storage":
[]},
{"block":214650,"size":0,"storage":
[]},
{"block":214651,"size":0,"storage":
[]},
{"block":214652,"size":0,"storage":
[]},
{"block":214653,"size":0,"storage":
[]},
{"block":214654,"size":0,"storage":
[]},
{"block":214655,"size":0,"storage":
[]},
{"block":214656,"size":0,"storage":
[]},
{"block":214657,"size":0,"storage":
[]},
{"block":214658,"size":0,"storage":
[]},
{"block":214659,"size":0,"storage":
[]},
{"block":214660,"size":0,"storage":
[]},
{"block":214661,"size":0,"storage":
[]},
{"block":214662,"size":0,"storage":
[]},
{"block":214663,"size":0,"storage":
[]},
{"block":214664,"size":0,"storage":
[]},
{"block":214665,"size":0,"storage":
[]},
{"block":214666,"size":0,"storage":
[]},
{"block":214667,"size":0,"storage":
[]},
{"block":214668,"size":0,"storage":
[]},
{"block":214669,"size":0,"storage":
[]},
{"block":214670,"size":0,"storage":
[]},
{"block":214671,"size":0,"storage":
[]},
{"block":214672,"size":0,"storage":
[]},
{"block":214673,"size":0,"storage":
[]},
{"block":214674,"size":0,"storage":
[]},
{"block":214675,"size":0,"storage":
[]},
{"block":214676,"size":0,"storage":
[]},
{"block":214677,"size":0,"storage":
[]},
{"block":214678,"size":0,"storage":
[]},
{"block":214679,"size":0,"storage":
[]},
{"block":214680,"size":0,"storage":
[]},
{"block":214681,"size":0,"storage":
[]},
{"block":214682,"size":0,"storage":
[]},
{"block":214683,"size":0,"storage":
[]},
{"block":214684,"size":0,"storage":
[]},
{"block":214685,"size":0,"storage":
[]},
{"block":214686,"size":0,"storage":
[]},
{"block":214687,"size":0,"storage":
[]},
{"block":214688,"size":0,"storage":
[]},
{"block":214689,"size":0,"storage":
[]},
{"block":214690,"size":0,"storage":
[]},
{"block":214691,"size":0,"storage":
[]},
{"block":214692,"size":0,"storage":
[]},
{"block":214693,"size":0,"storage":
[]},
{"block":214694,"size":0,"storage":
[]},
{"block":214695,"size":0,"storage":
[]},
{"block":214696,"size":0,"storage":
[]},
{"block":214697,"size":0,"storage":
[]},
{"block":214698,"size":0,"storage":
[]},
{"block":214699,"size":0,"storage":
[]},
{"block":214700,"size":0,"storage":
[]},
{"block":214701,"size":0,"storage":
[]},
{"block":214702,"size":0,"storage":
[]},
{"block":214703,"size":0,"storage":
[]},
{"block":214704,"size":0,"storage":
[]},
{"block":214705,"size":0,"storage":
[]},
{"block":214706,"size":0,"storage":
[]},
{"block":214707,"size":0,"storage":
[]},
{"block":214708,"size":0,"storage":
[]},
{"block":214709,"size":0,"storage":
[]},
{"block":214710,"size":0,"storage":
[]},
{"block":214711,"size":0,"storage":
[]},
{"block":214712,"size":0,"storage":
[]},
{"block":214713,"size":0,"storage":
[]},
{"block":214714,"size":0,"storage":
[]},
{"block":214715,"size":0,"storage":
[]},
{"block":214716,"size":0,"storage":
[]},
{"block":214717,"size":0,"storage":
[]},
{"block":214718,"size":0,"storage":
[]},
{"block":214719,"size":0,"storage":
[]},
{"block":214720,"size":0,"storage":
[]},
{"block":214721,"size":0,"storage":
[]},
{"block":214722,"size":0,"storage":
[]},
{"block":214723,"size":0,"storage":
[]},
{"block":214724,"size":0,"storage":
[]},
{"block":214725,"size":0,"storage":
[]},
{"block":214726,"size":0,"storage":
[]},
{"block":214727,"size":0,"storage":
[]},
{"block":214728,"size":0,"storage":
[]},
{"block":214729,"size":0,"storage":
[]},
{"block":214730,"size":0,"storage":
[]},
{"block":214731,"size":0,"storage":
[]},
{"block":214732,"size":0,"storage":
[]},
{"block":214733,"size":0,"storage":
[]},
{"block":214734,"size":0,"storage":
[]},
{"block":214735,"size":0,"storage":
[]},
{"block":214736,"size":0,"storage":
[]},
{"block":214737,"size":0,"storage":
[]},
{"block":214738,"size":0,"storage":
[]},
{"block":214739,"size":0,"storage":
[]},
{"block":214740,"size":0,"storage":
[]},
{"block":214741,"size":0,"storage":
[]},
{"block":214742,"size":0,"storage":
[]},
{"block":214743,"size":0,"storage":
[]},
{"block":214744,"size":0,"storage":
[]},
{"block":214745,"size":0,"storage":
[]},
{"block":214746,"size":0,"storage":
[]},
{"block":214747,"size":0,"storage":
[]},
{"block":214748,"size":0,"storage":
[]},
{"block":214749,"size":0,"storage":
[]},
{"block":214750,"size":0,"storage":
[]},
{"block":214751,"size":0,"storage":
[]},
{"block":214752,"size":0,"storage":
[]},
{"block":214753,"size":0,"storage":
[]},
{"block":214754,"size":0,"storage":
[]},
{"block":214755,"size":0,"storage":
[]},
{"block":214756,"size":0,"storage":
[]},
{"block":214757,"size":0,"storage":
[]},
{"block":214758,"size":0,"storage":
[]},
{"block":214759,"size":0,"storage":
[]},
{"block":214760,"size":0,"storage":
[]},
{"block":214761,"size":0,"storage":
[]},
{"block":214762,"size":0,"storage":
[]},
{"block":214763,"size":0,"storage":
[]},
{"block":214764,"size":0,"storage":
[]},
{"block":214765,"size":0,"storage":
[]},
{"block":214766,"size":0,"storage":
[]},
{"block":214767,"size":0,"storage":
[]},
{"block":214768,"size":0,"storage":
[]},
{"block":214769,"size":0,"storage":
[]},
{"block":214770,"size":0,"storage":
[]},
{"block":214771,"size":0,"storage":
[]},
{"block":214772,"size":0,"storage":
[]},
{"block":214773,"size":0,"storage":
[]},
{"block":214774,"size":0,"storage":
[]},
{"block":214775,"size":0,"storage":
[]},
{"block":214776,"size":0,"storage":
[]},
{"block":214777,"size":0,"storage":
[]},
{"block":214778,"size":0,"storage":
[]},
{"block":214779,"size":0,"storage":
[]},
{"block":214780,"size":0,"storage":
[]},
{"block":214781,"size":0,"storage":
[]},
{"block":214782,"size":0,"storage":
[]},
{"block":214783,"size":0,"storage":
[]},
{"block":214784,"size":0,"storage":
[]},
{"block":214785,"size":0,"storage":
[]},
{"block":214786,"size":0,"storage":
[]},
{"block":214787,"size":0,"storage":
[]},
{"block":214788,"size":0,"storage":
[]},
{"block":214789,"size":0,"storage":
[]},
{"block":214790,"size":0,"storage":
[]},
{"block":214791,"size":0,"storage":
[]},
{"block":214792,"size":0,"storage":
[]},
{"block":214793,"size":0,"storage":
[]},
{"block":214794,"size":0,"storage":
[]},
{"block":214795,"size":0,"storage":
[]},
{"block":214796,"size":0,"storage":
[]},
{"block":214797,"size":0,"storage":
[]},
{"block":214798,"size":0,"storage":
[]},
{"block":214799,"size":0,"storage":
[]},
{"block":214800,"size":0,"storage":
[]},
{"block":214801,"size":0,"storage":
[]},
{"block":214802,"size":0,"storage":
[]},
{"block":214803,"size":0,"storage":
[]},
{"block":214804,"size":0,"storage":
[]},
{"block":214805,"size":0,"storage":
[]},
{"block":214806,"size":0,"storage":
[]},
{"block":214807,"size":0,"storage":
[]},
{"block":214808,"size":0,"storage":
[]},
{"block":214809,"size":0,"storage":
[]},
{"block":214810,"size":0,"storage":
[]},
{"block":214811,"size":0,"storage":
[]},
{"block":214812,"size":0,"storage":
[]},
{"block":214813,"size":0,"storage":
[]},
{"block":214814,"size":0,"storage":
[]},
{"block":214815,"size":0,"storage":
[]},
{"block":214816,"size":0,"storage":
[]},
{"block":214817,"size":0,"storage":
[]},
{"block":214818,"size":0,"storage":
[]},
{"block":214819,"size":0,"storage":
[]},
{"block":214820,"size":0,"storage":
[]},
{"block":214821,"size":0,"storage":
[]},
{"block":214822,"size":0,"storage":
[]},
{"block":214823,"size":0,"storage":
[]},
{"block":214824,"size":0,"storage":
[]},
{"block":214825,"size":0,"storage":
[]},
{"block":214826,"size":0,"storage":
[]},
{"block":214827,"size":0,"storage":
[]},
{"block":214828,"size":0,"storage":
[]},
{"block":214829,"size":0,"storage":
[]},
{"block":214830,"size":0,"storage":
[]},
{"block":214831,"size":0,"storage":
[]},
{"block":214832,"size":0,"storage":
[]},
{"block":214833,"size":0,"storage":
[]},
{"block":214834,"size":0,"storage":
[]},
{"block":214835,"size":0,"storage":
[]},
{"block":214836,"size":0,"storage":
[]},
{"block":214837,"size":0,"storage":
[]},
{"block":214838,"size":0,"storage":
[]},
{"block":214839,"size":0,"storage":
[]},
{"block":214840,"size":0,"storage":
[]},
{"block":214841,"size":0,"storage":
[]},
{"block":214842,"size":0,"storage":
[]},
{"block":214843,"size":0,"storage":
[]},
{"block":214844,"size":0,"storage":
[]},
{"block":214845,"size":0,"storage":
[]},
{"block":214846,"size":0,"storage":
[]},
{"block":214847,"size":0,"storage":
[]},
{"block":214848,"size":0,"storage":
[]},
{"block":214849,"size":0,"storage":
[]},
{"block":214850,"size":0,"storage":
[]},
{"block":214851,"size":0,"storage":
[]},
{"block":214852,"size":0,"storage":
[]},
{"block":214853,"size":0,"storage":
[]},
{"block":214854,"size":0,"storage":
[]},
{"block":214855,"size":0,"storage":
[]},
{"block":214856,"size":0,"storage":
[]},
{"block":214857,"size":0,"storage":
[]},
{"block":214858,"size":0,"storage":
[]},
{"block":214859,"size":0,"storage":
[]},
{"block":214860,"size":0,"storage":
[]},
{"block":214861,"size":0,"storage":
[]},
{"block":214862,"size":0,"storage":
[]},
{"block":214863,"size":0,"storage":
[]},
{"block":214864,"size":0,"storage":
[]},
{"block":214865,"size":0,"storage":
[]},
{"block":214866,"size":0,"storage":
[]},
{"block":214867,"size":0,"storage":
[]},
{"block":214868,"size":0,"storage":
[]},
{"block":214869,"size":0,"storage":
[]},
{"block":214870,"size":0,"storage":
[]},
{"block":214871,"size":0,"storage":
[]},
{"block":214872,"size":0,"storage":
[]},
{"block":214873,"size":0,"storage":
[]},
{"block":214874,"size":0,"storage":
[]},
{"block":214875,"size":0,"storage":
[]},
{"block":214876,"size":0,"storage":
[]},
{"block":214877,"size":0,"storage":
[]},
{"block":214878,"size":0,"storage":
[]},
{"block":214879,"size":0,"storage":
[]},
{"block":214880,"size":0,"storage":
[]},
{"block":214881,"size":0,"storage":
[]},
{"block":214882,"size":0,"storage":
[]},
{"block":214883,"size":0,"storage":
[]},
{"block":214884,"size":0,"storage":
[]},
{"block":214885,"size":0,"storage":
[]},
{"block":214886,"size":0,"storage":
[]},
{"block":214887,"size":0,"storage":
[]},
{"block":214888,"size":0,"storage":
[]},
{"block":214889,"size":0,"storage":
[]},
{"block":214890,"size":0,"storage":
[]},
{"block":214891,"size":0,"storage":
[]},
{"block":214892,"size":0,"storage":
[]},
{"block":214893,"size":0,"storage":
[]},
{"block":214894,"size":0,"storage":
[]},
{"block":214895,"size":0,"storage":
[]},
{"block":214896,"size":0,"storage":
[]},
{"block":214897,"size":0,"storage":
[]},
{"block":214898,"size":0,"storage":
[]},
{"block":214899,"size":0,"storage":
[]},
{"block":214900,"size":0,"storage":
[]},
{"block":214901,"size":0,"storage":
[]},
{"block":214902,"size":0,"storage":
[]},
{"block":214903,"size":0,"storage":
[]},
{"block":214904,"size":0,"storage":
[]},
{"block":214905,"size":0,"storage":
[]},
{"block":214906,"size":0,"storage":
[]},
{"block":214907,"size":0,"storage":
[]},
{"block":214908,"size":0,"storage":
[]},
{"block":214909,"size":0,"storage":
[]},
{"block":214910,"size":0,"storage":
[]},
{"block":214911,"size":0,"storage":
[]},
{"block":214912,"size":0,"storage":
[]},
{"block":214913,"size":0,"storage":
[]},
{"block":214914,"size":0,"storage":
[]},
{"block":214915,"size":0,"storage":
[]},
{"block":214916,"size":0,"storage":
[]},
{"block":214917,"size":0,"storage":
[]},
{"block":214918,"size":0,"storage":
[]},
{"block":214919,"size":0,"storage":
[]},
{"block":214920,"size":0,"storage":
[]},
{"block":214921,"size":0,"storage":
[]},
{"block":214922,"size":0,"storage":
[]},
{"block":214923,"size":0,"storage":
[]},
{"block":214924,"size":0,"storage":
[]},
{"block":214925,"size":0,"storage":
[]},
{"block":214926,"size":0,"storage":
[]},
{"block":214927,"size":0,"storage":
[]},
{"block":214928,"size":0,"storage":
[]},
{"block":214929,"size":0,"storage":
[]},
{"block":214930,"size":0,"storage":
[]},
{"block":214931,"size":0,"storage":
[]},
{"block":214932,"size":0,"storage":
[]},
{"block":214933,"size":0,"storage":
[]},
{"block":214934,"size":0,"storage":
[]},
{"block":214935,"size":0,"storage":
[]},
{"block":214936,"size":0,"storage":
[]},
{"block":214937,"size":0,"storage":
[]},
{"block":214938,"size":0,"storage":
[]},
{"block":214939,"size":0,"storage":
[]},
{"block":214940,"size":0,"storage":
[]},
{"block":214941,"size":0,"storage":
[]},
{"block":214942,"size":0,"storage":
[]},
{"block":214943,"size":0,"storage":
[]},
{"block":214944,"size":0,"storage":
[]},
{"block":214945,"size":0,"storage":
[]},
{"block":214946,"size":0,"storage":
[]},
{"block":214947,"size":0,"storage":
[]},
{"block":214948,"size":0,"storage":
[]},
{"block":214949,"size":0,"storage":
[]},
{"block":214950,"size":0,"storage":
[]},
{"block":214951,"size":0,"storage":
[]},
{"block":214952,"size":0,"storage":
[]},
{"block":214953,"size":0,"storage":
[]},
{"block":214954,"size":0,"storage":
[]},
{"block":214955,"size":0,"storage":
[]},
{"block":214956,"size":0,"storage":
[]},
{"block":214957,"size":0,"storage":
[]},
{"block":214958,"size":0,"storage":
[]},
{"block":214959,"size":0,"storage":
[]},
{"block":214960,"size":0,"storage":
[]},
{"block":214961,"size":0,"storage":
[]},
{"block":214962,"size":0,"storage":
[]},
{"block":214963,"size":0,"storage":
[]},
{"block":214964,"size":0,"storage":
[]},
{"block":214965,"size":0,"storage":
[]},
{"block":214966,"size":0,"storage":
[]},
{"block":214967,"size":0,"storage":
[]},
{"block":214968,"size":0,"storage":
[]},
{"block":214969,"size":0,"storage":
[]},
{"block":214970,"size":0,"storage":
[]},
{"block":214971,"size":0,"storage":
[]},
{"block":214972,"size":0,"storage":
[]},
{"block":214973,"size":0,"storage":
[]},
{"block":214974,"size":0,"storage":
[]},
{"block":214975,"size":0,"storage":
[]},
{"block":214976,"size":0,"storage":
[]},
{"block":214977,"size":0,"storage":
[]},
{"block":214978,"size":0,"storage":
[]},
{"block":214979,"size":0,"storage":
[]},
{"block":214980,"size":0,"storage":
[]},
{"block":214981,"size":0,"storage":
[]},
{"block":214982,"size":0,"storage":
[]},
{"block":214983,"size":0,"storage":
[]},
{"block":214984,"size":0,"storage":
[]},
{"block":214985,"size":0,"storage":
[]},
{"block":214986,"size":0,"storage":
[]},
{"block":214987,"size":0,"storage":
[]},
{"block":214988,"size":0,"storage":
[]},
{"block":214989,"size":0,"storage":
[]},
{"block":214990,"size":0,"storage":
[]},
{"block":214991,"size":0,"storage":
[]},
{"block":214992,"size":0,"storage":
[]},
{"block":214993,"size":0,"storage":
[]},
{"block":214994,"size":0,"storage":
[]},
{"block":214995,"size":0,"storage":
[]},
{"block":214996,"size":0,"storage":
[]},
{"block":214997,"size":0,"storage":
[]},
{"block":214998,"size":0,"storage":
[]},
{"block":214999,"size":0,"storage":
[]},
{"block":215000,"size":0,"storage":
[]},
]