[{"block":1115001,"size":0,"storage":
[]},
{"block":1115002,"size":0,"storage":
[]},
{"block":1115003,"size":0,"storage":
[]},
{"block":1115004,"size":0,"storage":
[]},
{"block":1115005,"size":0,"storage":
[]},
{"block":1115006,"size":0,"storage":
[]},
{"block":1115007,"size":0,"storage":
[]},
{"block":1115008,"size":0,"storage":
[]},
{"block":1115009,"size":0,"storage":
[]},
{"block":1115010,"size":0,"storage":
[]},
{"block":1115011,"size":0,"storage":
[]},
{"block":1115012,"size":0,"storage":
[]},
{"block":1115013,"size":0,"storage":
[]},
{"block":1115014,"size":0,"storage":
[]},
{"block":1115015,"size":0,"storage":
[]},
{"block":1115016,"size":0,"storage":
[]},
{"block":1115017,"size":0,"storage":
[]},
{"block":1115018,"size":0,"storage":
[]},
{"block":1115019,"size":0,"storage":
[]},
{"block":1115020,"size":0,"storage":
[]},
{"block":1115021,"size":0,"storage":
[]},
{"block":1115022,"size":0,"storage":
[]},
{"block":1115023,"size":0,"storage":
[]},
{"block":1115024,"size":0,"storage":
[]},
{"block":1115025,"size":0,"storage":
[]},
{"block":1115026,"size":0,"storage":
[]},
{"block":1115027,"size":0,"storage":
[]},
{"block":1115028,"size":0,"storage":
[]},
{"block":1115029,"size":0,"storage":
[]},
{"block":1115030,"size":0,"storage":
[]},
{"block":1115031,"size":0,"storage":
[]},
{"block":1115032,"size":0,"storage":
[]},
{"block":1115033,"size":0,"storage":
[]},
{"block":1115034,"size":0,"storage":
[]},
{"block":1115035,"size":0,"storage":
[]},
{"block":1115036,"size":0,"storage":
[]},
{"block":1115037,"size":0,"storage":
[]},
{"block":1115038,"size":0,"storage":
[]},
{"block":1115039,"size":0,"storage":
[]},
{"block":1115040,"size":0,"storage":
[]},
{"block":1115041,"size":0,"storage":
[]},
{"block":1115042,"size":0,"storage":
[]},
{"block":1115043,"size":0,"storage":
[]},
{"block":1115044,"size":0,"storage":
[]},
{"block":1115045,"size":0,"storage":
[]},
{"block":1115046,"size":0,"storage":
[]},
{"block":1115047,"size":0,"storage":
[]},
{"block":1115048,"size":0,"storage":
[]},
{"block":1115049,"size":0,"storage":
[]},
{"block":1115050,"size":0,"storage":
[]},
{"block":1115051,"size":0,"storage":
[]},
{"block":1115052,"size":0,"storage":
[]},
{"block":1115053,"size":0,"storage":
[]},
{"block":1115054,"size":0,"storage":
[]},
{"block":1115055,"size":0,"storage":
[]},
{"block":1115056,"size":0,"storage":
[]},
{"block":1115057,"size":0,"storage":
[]},
{"block":1115058,"size":0,"storage":
[]},
{"block":1115059,"size":0,"storage":
[]},
{"block":1115060,"size":0,"storage":
[]},
{"block":1115061,"size":0,"storage":
[]},
{"block":1115062,"size":0,"storage":
[]},
{"block":1115063,"size":0,"storage":
[]},
{"block":1115064,"size":0,"storage":
[]},
{"block":1115065,"size":0,"storage":
[]},
{"block":1115066,"size":0,"storage":
[]},
{"block":1115067,"size":0,"storage":
[]},
{"block":1115068,"size":0,"storage":
[]},
{"block":1115069,"size":0,"storage":
[]},
{"block":1115070,"size":0,"storage":
[]},
{"block":1115071,"size":0,"storage":
[]},
{"block":1115072,"size":0,"storage":
[]},
{"block":1115073,"size":0,"storage":
[]},
{"block":1115074,"size":0,"storage":
[]},
{"block":1115075,"size":0,"storage":
[]},
{"block":1115076,"size":0,"storage":
[]},
{"block":1115077,"size":0,"storage":
[]},
{"block":1115078,"size":0,"storage":
[]},
{"block":1115079,"size":0,"storage":
[]},
{"block":1115080,"size":0,"storage":
[]},
{"block":1115081,"size":0,"storage":
[]},
{"block":1115082,"size":0,"storage":
[]},
{"block":1115083,"size":0,"storage":
[]},
{"block":1115084,"size":0,"storage":
[]},
{"block":1115085,"size":0,"storage":
[]},
{"block":1115086,"size":0,"storage":
[]},
{"block":1115087,"size":0,"storage":
[]},
{"block":1115088,"size":0,"storage":
[]},
{"block":1115089,"size":0,"storage":
[]},
{"block":1115090,"size":0,"storage":
[]},
{"block":1115091,"size":0,"storage":
[]},
{"block":1115092,"size":0,"storage":
[]},
{"block":1115093,"size":0,"storage":
[]},
{"block":1115094,"size":0,"storage":
[]},
{"block":1115095,"size":0,"storage":
[]},
{"block":1115096,"size":0,"storage":
[]},
{"block":1115097,"size":0,"storage":
[]},
{"block":1115098,"size":0,"storage":
[]},
{"block":1115099,"size":0,"storage":
[]},
{"block":1115100,"size":0,"storage":
[]},
{"block":1115101,"size":0,"storage":
[]},
{"block":1115102,"size":0,"storage":
[]},
{"block":1115103,"size":0,"storage":
[]},
{"block":1115104,"size":0,"storage":
[]},
{"block":1115105,"size":0,"storage":
[]},
{"block":1115106,"size":0,"storage":
[]},
{"block":1115107,"size":0,"storage":
[]},
{"block":1115108,"size":0,"storage":
[]},
{"block":1115109,"size":0,"storage":
[]},
{"block":1115110,"size":0,"storage":
[]},
{"block":1115111,"size":0,"storage":
[]},
{"block":1115112,"size":0,"storage":
[]},
{"block":1115113,"size":0,"storage":
[]},
{"block":1115114,"size":0,"storage":
[]},
{"block":1115115,"size":0,"storage":
[]},
{"block":1115116,"size":0,"storage":
[]},
{"block":1115117,"size":0,"storage":
[]},
{"block":1115118,"size":0,"storage":
[]},
{"block":1115119,"size":0,"storage":
[]},
{"block":1115120,"size":0,"storage":
[]},
{"block":1115121,"size":0,"storage":
[]},
{"block":1115122,"size":0,"storage":
[]},
{"block":1115123,"size":0,"storage":
[]},
{"block":1115124,"size":0,"storage":
[]},
{"block":1115125,"size":0,"storage":
[]},
{"block":1115126,"size":0,"storage":
[]},
{"block":1115127,"size":0,"storage":
[]},
{"block":1115128,"size":0,"storage":
[]},
{"block":1115129,"size":0,"storage":
[]},
{"block":1115130,"size":0,"storage":
[]},
{"block":1115131,"size":0,"storage":
[]},
{"block":1115132,"size":0,"storage":
[]},
{"block":1115133,"size":0,"storage":
[]},
{"block":1115134,"size":0,"storage":
[]},
{"block":1115135,"size":0,"storage":
[]},
{"block":1115136,"size":0,"storage":
[]},
{"block":1115137,"size":0,"storage":
[]},
{"block":1115138,"size":0,"storage":
[]},
{"block":1115139,"size":0,"storage":
[]},
{"block":1115140,"size":0,"storage":
[]},
{"block":1115141,"size":0,"storage":
[]},
{"block":1115142,"size":0,"storage":
[]},
{"block":1115143,"size":0,"storage":
[]},
{"block":1115144,"size":0,"storage":
[]},
{"block":1115145,"size":0,"storage":
[]},
{"block":1115146,"size":0,"storage":
[]},
{"block":1115147,"size":0,"storage":
[]},
{"block":1115148,"size":0,"storage":
[]},
{"block":1115149,"size":0,"storage":
[]},
{"block":1115150,"size":0,"storage":
[]},
{"block":1115151,"size":0,"storage":
[]},
{"block":1115152,"size":0,"storage":
[]},
{"block":1115153,"size":0,"storage":
[]},
{"block":1115154,"size":0,"storage":
[]},
{"block":1115155,"size":0,"storage":
[]},
{"block":1115156,"size":0,"storage":
[]},
{"block":1115157,"size":0,"storage":
[]},
{"block":1115158,"size":0,"storage":
[]},
{"block":1115159,"size":0,"storage":
[]},
{"block":1115160,"size":0,"storage":
[]},
{"block":1115161,"size":0,"storage":
[]},
{"block":1115162,"size":0,"storage":
[]},
{"block":1115163,"size":0,"storage":
[]},
{"block":1115164,"size":0,"storage":
[]},
{"block":1115165,"size":0,"storage":
[]},
{"block":1115166,"size":0,"storage":
[]},
{"block":1115167,"size":0,"storage":
[]},
{"block":1115168,"size":0,"storage":
[]},
{"block":1115169,"size":0,"storage":
[]},
{"block":1115170,"size":0,"storage":
[]},
{"block":1115171,"size":0,"storage":
[]},
{"block":1115172,"size":0,"storage":
[]},
{"block":1115173,"size":0,"storage":
[]},
{"block":1115174,"size":0,"storage":
[]},
{"block":1115175,"size":0,"storage":
[]},
{"block":1115176,"size":0,"storage":
[]},
{"block":1115177,"size":0,"storage":
[]},
{"block":1115178,"size":0,"storage":
[]},
{"block":1115179,"size":0,"storage":
[]},
{"block":1115180,"size":0,"storage":
[]},
{"block":1115181,"size":0,"storage":
[]},
{"block":1115182,"size":0,"storage":
[]},
{"block":1115183,"size":0,"storage":
[]},
{"block":1115184,"size":0,"storage":
[]},
{"block":1115185,"size":0,"storage":
[]},
{"block":1115186,"size":0,"storage":
[]},
{"block":1115187,"size":0,"storage":
[]},
{"block":1115188,"size":0,"storage":
[]},
{"block":1115189,"size":0,"storage":
[]},
{"block":1115190,"size":0,"storage":
[]},
{"block":1115191,"size":0,"storage":
[]},
{"block":1115192,"size":0,"storage":
[]},
{"block":1115193,"size":0,"storage":
[]},
{"block":1115194,"size":0,"storage":
[]},
{"block":1115195,"size":0,"storage":
[]},
{"block":1115196,"size":0,"storage":
[]},
{"block":1115197,"size":0,"storage":
[]},
{"block":1115198,"size":0,"storage":
[]},
{"block":1115199,"size":0,"storage":
[]},
{"block":1115200,"size":0,"storage":
[]},
{"block":1115201,"size":0,"storage":
[]},
{"block":1115202,"size":0,"storage":
[]},
{"block":1115203,"size":0,"storage":
[]},
{"block":1115204,"size":0,"storage":
[]},
{"block":1115205,"size":0,"storage":
[]},
{"block":1115206,"size":0,"storage":
[]},
{"block":1115207,"size":0,"storage":
[]},
{"block":1115208,"size":0,"storage":
[]},
{"block":1115209,"size":0,"storage":
[]},
{"block":1115210,"size":0,"storage":
[]},
{"block":1115211,"size":0,"storage":
[]},
{"block":1115212,"size":0,"storage":
[]},
{"block":1115213,"size":0,"storage":
[]},
{"block":1115214,"size":0,"storage":
[]},
{"block":1115215,"size":0,"storage":
[]},
{"block":1115216,"size":0,"storage":
[]},
{"block":1115217,"size":0,"storage":
[]},
{"block":1115218,"size":0,"storage":
[]},
{"block":1115219,"size":0,"storage":
[]},
{"block":1115220,"size":0,"storage":
[]},
{"block":1115221,"size":0,"storage":
[]},
{"block":1115222,"size":0,"storage":
[]},
{"block":1115223,"size":0,"storage":
[]},
{"block":1115224,"size":0,"storage":
[]},
{"block":1115225,"size":0,"storage":
[]},
{"block":1115226,"size":0,"storage":
[]},
{"block":1115227,"size":0,"storage":
[]},
{"block":1115228,"size":0,"storage":
[]},
{"block":1115229,"size":0,"storage":
[]},
{"block":1115230,"size":0,"storage":
[]},
{"block":1115231,"size":0,"storage":
[]},
{"block":1115232,"size":0,"storage":
[]},
{"block":1115233,"size":0,"storage":
[]},
{"block":1115234,"size":0,"storage":
[]},
{"block":1115235,"size":0,"storage":
[]},
{"block":1115236,"size":0,"storage":
[]},
{"block":1115237,"size":0,"storage":
[]},
{"block":1115238,"size":0,"storage":
[]},
{"block":1115239,"size":0,"storage":
[]},
{"block":1115240,"size":0,"storage":
[]},
{"block":1115241,"size":0,"storage":
[]},
{"block":1115242,"size":0,"storage":
[]},
{"block":1115243,"size":0,"storage":
[]},
{"block":1115244,"size":0,"storage":
[]},
{"block":1115245,"size":0,"storage":
[]},
{"block":1115246,"size":0,"storage":
[]},
{"block":1115247,"size":0,"storage":
[]},
{"block":1115248,"size":0,"storage":
[]},
{"block":1115249,"size":0,"storage":
[]},
{"block":1115250,"size":0,"storage":
[]},
{"block":1115251,"size":0,"storage":
[]},
{"block":1115252,"size":0,"storage":
[]},
{"block":1115253,"size":0,"storage":
[]},
{"block":1115254,"size":0,"storage":
[]},
{"block":1115255,"size":0,"storage":
[]},
{"block":1115256,"size":0,"storage":
[]},
{"block":1115257,"size":0,"storage":
[]},
{"block":1115258,"size":0,"storage":
[]},
{"block":1115259,"size":0,"storage":
[]},
{"block":1115260,"size":0,"storage":
[]},
{"block":1115261,"size":0,"storage":
[]},
{"block":1115262,"size":0,"storage":
[]},
{"block":1115263,"size":0,"storage":
[]},
{"block":1115264,"size":0,"storage":
[]},
{"block":1115265,"size":0,"storage":
[]},
{"block":1115266,"size":0,"storage":
[]},
{"block":1115267,"size":0,"storage":
[]},
{"block":1115268,"size":0,"storage":
[]},
{"block":1115269,"size":0,"storage":
[]},
{"block":1115270,"size":0,"storage":
[]},
{"block":1115271,"size":0,"storage":
[]},
{"block":1115272,"size":0,"storage":
[]},
{"block":1115273,"size":0,"storage":
[]},
{"block":1115274,"size":0,"storage":
[]},
{"block":1115275,"size":0,"storage":
[]},
{"block":1115276,"size":0,"storage":
[]},
{"block":1115277,"size":0,"storage":
[]},
{"block":1115278,"size":0,"storage":
[]},
{"block":1115279,"size":0,"storage":
[]},
{"block":1115280,"size":0,"storage":
[]},
{"block":1115281,"size":0,"storage":
[]},
{"block":1115282,"size":0,"storage":
[]},
{"block":1115283,"size":0,"storage":
[]},
{"block":1115284,"size":0,"storage":
[]},
{"block":1115285,"size":0,"storage":
[]},
{"block":1115286,"size":0,"storage":
[]},
{"block":1115287,"size":0,"storage":
[]},
{"block":1115288,"size":0,"storage":
[]},
{"block":1115289,"size":0,"storage":
[]},
{"block":1115290,"size":0,"storage":
[]},
{"block":1115291,"size":0,"storage":
[]},
{"block":1115292,"size":0,"storage":
[]},
{"block":1115293,"size":0,"storage":
[]},
{"block":1115294,"size":0,"storage":
[]},
{"block":1115295,"size":0,"storage":
[]},
{"block":1115296,"size":0,"storage":
[]},
{"block":1115297,"size":0,"storage":
[]},
{"block":1115298,"size":0,"storage":
[]},
{"block":1115299,"size":0,"storage":
[]},
{"block":1115300,"size":0,"storage":
[]},
{"block":1115301,"size":0,"storage":
[]},
{"block":1115302,"size":0,"storage":
[]},
{"block":1115303,"size":0,"storage":
[]},
{"block":1115304,"size":0,"storage":
[]},
{"block":1115305,"size":0,"storage":
[]},
{"block":1115306,"size":0,"storage":
[]},
{"block":1115307,"size":0,"storage":
[]},
{"block":1115308,"size":0,"storage":
[]},
{"block":1115309,"size":0,"storage":
[]},
{"block":1115310,"size":0,"storage":
[]},
{"block":1115311,"size":0,"storage":
[]},
{"block":1115312,"size":0,"storage":
[]},
{"block":1115313,"size":0,"storage":
[]},
{"block":1115314,"size":0,"storage":
[]},
{"block":1115315,"size":0,"storage":
[]},
{"block":1115316,"size":0,"storage":
[]},
{"block":1115317,"size":0,"storage":
[]},
{"block":1115318,"size":0,"storage":
[]},
{"block":1115319,"size":0,"storage":
[]},
{"block":1115320,"size":0,"storage":
[]},
{"block":1115321,"size":0,"storage":
[]},
{"block":1115322,"size":0,"storage":
[]},
{"block":1115323,"size":0,"storage":
[]},
{"block":1115324,"size":0,"storage":
[]},
{"block":1115325,"size":0,"storage":
[]},
{"block":1115326,"size":0,"storage":
[]},
{"block":1115327,"size":0,"storage":
[]},
{"block":1115328,"size":0,"storage":
[]},
{"block":1115329,"size":0,"storage":
[]},
{"block":1115330,"size":0,"storage":
[]},
{"block":1115331,"size":0,"storage":
[]},
{"block":1115332,"size":0,"storage":
[]},
{"block":1115333,"size":0,"storage":
[]},
{"block":1115334,"size":0,"storage":
[]},
{"block":1115335,"size":0,"storage":
[]},
{"block":1115336,"size":0,"storage":
[]},
{"block":1115337,"size":0,"storage":
[]},
{"block":1115338,"size":0,"storage":
[]},
{"block":1115339,"size":0,"storage":
[]},
{"block":1115340,"size":0,"storage":
[]},
{"block":1115341,"size":0,"storage":
[]},
{"block":1115342,"size":0,"storage":
[]},
{"block":1115343,"size":0,"storage":
[]},
{"block":1115344,"size":0,"storage":
[]},
{"block":1115345,"size":0,"storage":
[]},
{"block":1115346,"size":0,"storage":
[]},
{"block":1115347,"size":0,"storage":
[]},
{"block":1115348,"size":0,"storage":
[]},
{"block":1115349,"size":0,"storage":
[]},
{"block":1115350,"size":0,"storage":
[]},
{"block":1115351,"size":0,"storage":
[]},
{"block":1115352,"size":0,"storage":
[]},
{"block":1115353,"size":0,"storage":
[]},
{"block":1115354,"size":0,"storage":
[]},
{"block":1115355,"size":0,"storage":
[]},
{"block":1115356,"size":0,"storage":
[]},
{"block":1115357,"size":0,"storage":
[]},
{"block":1115358,"size":0,"storage":
[]},
{"block":1115359,"size":0,"storage":
[]},
{"block":1115360,"size":0,"storage":
[]},
{"block":1115361,"size":0,"storage":
[]},
{"block":1115362,"size":0,"storage":
[]},
{"block":1115363,"size":0,"storage":
[]},
{"block":1115364,"size":0,"storage":
[]},
{"block":1115365,"size":0,"storage":
[]},
{"block":1115366,"size":0,"storage":
[]},
{"block":1115367,"size":0,"storage":
[]},
{"block":1115368,"size":0,"storage":
[]},
{"block":1115369,"size":0,"storage":
[]},
{"block":1115370,"size":0,"storage":
[]},
{"block":1115371,"size":0,"storage":
[]},
{"block":1115372,"size":0,"storage":
[]},
{"block":1115373,"size":0,"storage":
[]},
{"block":1115374,"size":0,"storage":
[]},
{"block":1115375,"size":0,"storage":
[]},
{"block":1115376,"size":0,"storage":
[]},
{"block":1115377,"size":0,"storage":
[]},
{"block":1115378,"size":0,"storage":
[]},
{"block":1115379,"size":0,"storage":
[]},
{"block":1115380,"size":0,"storage":
[]},
{"block":1115381,"size":0,"storage":
[]},
{"block":1115382,"size":0,"storage":
[]},
{"block":1115383,"size":0,"storage":
[]},
{"block":1115384,"size":0,"storage":
[]},
{"block":1115385,"size":0,"storage":
[]},
{"block":1115386,"size":0,"storage":
[]},
{"block":1115387,"size":0,"storage":
[]},
{"block":1115388,"size":0,"storage":
[]},
{"block":1115389,"size":0,"storage":
[]},
{"block":1115390,"size":0,"storage":
[]},
{"block":1115391,"size":0,"storage":
[]},
{"block":1115392,"size":0,"storage":
[]},
{"block":1115393,"size":0,"storage":
[]},
{"block":1115394,"size":0,"storage":
[]},
{"block":1115395,"size":0,"storage":
[]},
{"block":1115396,"size":0,"storage":
[]},
{"block":1115397,"size":0,"storage":
[]},
{"block":1115398,"size":0,"storage":
[]},
{"block":1115399,"size":0,"storage":
[]},
{"block":1115400,"size":0,"storage":
[]},
{"block":1115401,"size":0,"storage":
[]},
{"block":1115402,"size":0,"storage":
[]},
{"block":1115403,"size":0,"storage":
[]},
{"block":1115404,"size":0,"storage":
[]},
{"block":1115405,"size":0,"storage":
[]},
{"block":1115406,"size":0,"storage":
[]},
{"block":1115407,"size":0,"storage":
[]},
{"block":1115408,"size":0,"storage":
[]},
{"block":1115409,"size":0,"storage":
[]},
{"block":1115410,"size":0,"storage":
[]},
{"block":1115411,"size":0,"storage":
[]},
{"block":1115412,"size":0,"storage":
[]},
{"block":1115413,"size":0,"storage":
[]},
{"block":1115414,"size":0,"storage":
[]},
{"block":1115415,"size":0,"storage":
[]},
{"block":1115416,"size":0,"storage":
[]},
{"block":1115417,"size":0,"storage":
[]},
{"block":1115418,"size":0,"storage":
[]},
{"block":1115419,"size":0,"storage":
[]},
{"block":1115420,"size":0,"storage":
[]},
{"block":1115421,"size":0,"storage":
[]},
{"block":1115422,"size":0,"storage":
[]},
{"block":1115423,"size":0,"storage":
[]},
{"block":1115424,"size":0,"storage":
[]},
{"block":1115425,"size":0,"storage":
[]},
{"block":1115426,"size":0,"storage":
[]},
{"block":1115427,"size":0,"storage":
[]},
{"block":1115428,"size":0,"storage":
[]},
{"block":1115429,"size":0,"storage":
[]},
{"block":1115430,"size":0,"storage":
[]},
{"block":1115431,"size":0,"storage":
[]},
{"block":1115432,"size":0,"storage":
[]},
{"block":1115433,"size":0,"storage":
[]},
{"block":1115434,"size":0,"storage":
[]},
{"block":1115435,"size":0,"storage":
[]},
{"block":1115436,"size":0,"storage":
[]},
{"block":1115437,"size":0,"storage":
[]},
{"block":1115438,"size":0,"storage":
[]},
{"block":1115439,"size":0,"storage":
[]},
{"block":1115440,"size":0,"storage":
[]},
{"block":1115441,"size":0,"storage":
[]},
{"block":1115442,"size":0,"storage":
[]},
{"block":1115443,"size":0,"storage":
[]},
{"block":1115444,"size":0,"storage":
[]},
{"block":1115445,"size":0,"storage":
[]},
{"block":1115446,"size":0,"storage":
[]},
{"block":1115447,"size":0,"storage":
[]},
{"block":1115448,"size":0,"storage":
[]},
{"block":1115449,"size":0,"storage":
[]},
{"block":1115450,"size":0,"storage":
[]},
{"block":1115451,"size":0,"storage":
[]},
{"block":1115452,"size":0,"storage":
[]},
{"block":1115453,"size":0,"storage":
[]},
{"block":1115454,"size":0,"storage":
[]},
{"block":1115455,"size":0,"storage":
[]},
{"block":1115456,"size":0,"storage":
[]},
{"block":1115457,"size":0,"storage":
[]},
{"block":1115458,"size":0,"storage":
[]},
{"block":1115459,"size":0,"storage":
[]},
{"block":1115460,"size":0,"storage":
[]},
{"block":1115461,"size":0,"storage":
[]},
{"block":1115462,"size":0,"storage":
[]},
{"block":1115463,"size":0,"storage":
[]},
{"block":1115464,"size":0,"storage":
[]},
{"block":1115465,"size":0,"storage":
[]},
{"block":1115466,"size":0,"storage":
[]},
{"block":1115467,"size":0,"storage":
[]},
{"block":1115468,"size":0,"storage":
[]},
{"block":1115469,"size":0,"storage":
[]},
{"block":1115470,"size":0,"storage":
[]},
{"block":1115471,"size":0,"storage":
[]},
{"block":1115472,"size":0,"storage":
[]},
{"block":1115473,"size":0,"storage":
[]},
{"block":1115474,"size":0,"storage":
[]},
{"block":1115475,"size":0,"storage":
[]},
{"block":1115476,"size":0,"storage":
[]},
{"block":1115477,"size":0,"storage":
[]},
{"block":1115478,"size":0,"storage":
[]},
{"block":1115479,"size":0,"storage":
[]},
{"block":1115480,"size":0,"storage":
[]},
{"block":1115481,"size":0,"storage":
[]},
{"block":1115482,"size":0,"storage":
[]},
{"block":1115483,"size":0,"storage":
[]},
{"block":1115484,"size":0,"storage":
[]},
{"block":1115485,"size":0,"storage":
[]},
{"block":1115486,"size":0,"storage":
[]},
{"block":1115487,"size":0,"storage":
[]},
{"block":1115488,"size":0,"storage":
[]},
{"block":1115489,"size":0,"storage":
[]},
{"block":1115490,"size":0,"storage":
[]},
{"block":1115491,"size":0,"storage":
[]},
{"block":1115492,"size":0,"storage":
[]},
{"block":1115493,"size":0,"storage":
[]},
{"block":1115494,"size":0,"storage":
[]},
{"block":1115495,"size":0,"storage":
[]},
{"block":1115496,"size":0,"storage":
[]},
{"block":1115497,"size":0,"storage":
[]},
{"block":1115498,"size":0,"storage":
[]},
{"block":1115499,"size":0,"storage":
[]},
{"block":1115500,"size":0,"storage":
[]},
{"block":1115501,"size":0,"storage":
[]},
{"block":1115502,"size":0,"storage":
[]},
{"block":1115503,"size":0,"storage":
[]},
{"block":1115504,"size":0,"storage":
[]},
{"block":1115505,"size":0,"storage":
[]},
{"block":1115506,"size":0,"storage":
[]},
{"block":1115507,"size":0,"storage":
[]},
{"block":1115508,"size":0,"storage":
[]},
{"block":1115509,"size":0,"storage":
[]},
{"block":1115510,"size":0,"storage":
[]},
{"block":1115511,"size":0,"storage":
[]},
{"block":1115512,"size":0,"storage":
[]},
{"block":1115513,"size":0,"storage":
[]},
{"block":1115514,"size":0,"storage":
[]},
{"block":1115515,"size":0,"storage":
[]},
{"block":1115516,"size":0,"storage":
[]},
{"block":1115517,"size":0,"storage":
[]},
{"block":1115518,"size":0,"storage":
[]},
{"block":1115519,"size":0,"storage":
[]},
{"block":1115520,"size":0,"storage":
[]},
{"block":1115521,"size":0,"storage":
[]},
{"block":1115522,"size":0,"storage":
[]},
{"block":1115523,"size":0,"storage":
[]},
{"block":1115524,"size":0,"storage":
[]},
{"block":1115525,"size":0,"storage":
[]},
{"block":1115526,"size":0,"storage":
[]},
{"block":1115527,"size":0,"storage":
[]},
{"block":1115528,"size":0,"storage":
[]},
{"block":1115529,"size":0,"storage":
[]},
{"block":1115530,"size":0,"storage":
[]},
{"block":1115531,"size":0,"storage":
[]},
{"block":1115532,"size":0,"storage":
[]},
{"block":1115533,"size":0,"storage":
[]},
{"block":1115534,"size":0,"storage":
[]},
{"block":1115535,"size":0,"storage":
[]},
{"block":1115536,"size":0,"storage":
[]},
{"block":1115537,"size":0,"storage":
[]},
{"block":1115538,"size":0,"storage":
[]},
{"block":1115539,"size":0,"storage":
[]},
{"block":1115540,"size":0,"storage":
[]},
{"block":1115541,"size":0,"storage":
[]},
{"block":1115542,"size":0,"storage":
[]},
{"block":1115543,"size":0,"storage":
[]},
{"block":1115544,"size":0,"storage":
[]},
{"block":1115545,"size":0,"storage":
[]},
{"block":1115546,"size":0,"storage":
[]},
{"block":1115547,"size":0,"storage":
[]},
{"block":1115548,"size":0,"storage":
[]},
{"block":1115549,"size":0,"storage":
[]},
{"block":1115550,"size":0,"storage":
[]},
{"block":1115551,"size":0,"storage":
[]},
{"block":1115552,"size":0,"storage":
[]},
{"block":1115553,"size":0,"storage":
[]},
{"block":1115554,"size":0,"storage":
[]},
{"block":1115555,"size":0,"storage":
[]},
{"block":1115556,"size":0,"storage":
[]},
{"block":1115557,"size":0,"storage":
[]},
{"block":1115558,"size":0,"storage":
[]},
{"block":1115559,"size":0,"storage":
[]},
{"block":1115560,"size":0,"storage":
[]},
{"block":1115561,"size":0,"storage":
[]},
{"block":1115562,"size":0,"storage":
[]},
{"block":1115563,"size":0,"storage":
[]},
{"block":1115564,"size":0,"storage":
[]},
{"block":1115565,"size":0,"storage":
[]},
{"block":1115566,"size":0,"storage":
[]},
{"block":1115567,"size":0,"storage":
[]},
{"block":1115568,"size":0,"storage":
[]},
{"block":1115569,"size":0,"storage":
[]},
{"block":1115570,"size":0,"storage":
[]},
{"block":1115571,"size":0,"storage":
[]},
{"block":1115572,"size":0,"storage":
[]},
{"block":1115573,"size":0,"storage":
[]},
{"block":1115574,"size":0,"storage":
[]},
{"block":1115575,"size":0,"storage":
[]},
{"block":1115576,"size":0,"storage":
[]},
{"block":1115577,"size":0,"storage":
[]},
{"block":1115578,"size":0,"storage":
[]},
{"block":1115579,"size":0,"storage":
[]},
{"block":1115580,"size":0,"storage":
[]},
{"block":1115581,"size":0,"storage":
[]},
{"block":1115582,"size":0,"storage":
[]},
{"block":1115583,"size":0,"storage":
[]},
{"block":1115584,"size":0,"storage":
[]},
{"block":1115585,"size":0,"storage":
[]},
{"block":1115586,"size":0,"storage":
[]},
{"block":1115587,"size":0,"storage":
[]},
{"block":1115588,"size":0,"storage":
[]},
{"block":1115589,"size":0,"storage":
[]},
{"block":1115590,"size":0,"storage":
[]},
{"block":1115591,"size":0,"storage":
[]},
{"block":1115592,"size":0,"storage":
[]},
{"block":1115593,"size":0,"storage":
[]},
{"block":1115594,"size":0,"storage":
[]},
{"block":1115595,"size":0,"storage":
[]},
{"block":1115596,"size":0,"storage":
[]},
{"block":1115597,"size":0,"storage":
[]},
{"block":1115598,"size":0,"storage":
[]},
{"block":1115599,"size":0,"storage":
[]},
{"block":1115600,"size":0,"storage":
[]},
{"block":1115601,"size":0,"storage":
[]},
{"block":1115602,"size":0,"storage":
[]},
{"block":1115603,"size":0,"storage":
[]},
{"block":1115604,"size":0,"storage":
[]},
{"block":1115605,"size":0,"storage":
[]},
{"block":1115606,"size":0,"storage":
[]},
{"block":1115607,"size":0,"storage":
[]},
{"block":1115608,"size":0,"storage":
[]},
{"block":1115609,"size":0,"storage":
[]},
{"block":1115610,"size":0,"storage":
[]},
{"block":1115611,"size":0,"storage":
[]},
{"block":1115612,"size":0,"storage":
[]},
{"block":1115613,"size":0,"storage":
[]},
{"block":1115614,"size":0,"storage":
[]},
{"block":1115615,"size":0,"storage":
[]},
{"block":1115616,"size":0,"storage":
[]},
{"block":1115617,"size":0,"storage":
[]},
{"block":1115618,"size":0,"storage":
[]},
{"block":1115619,"size":0,"storage":
[]},
{"block":1115620,"size":0,"storage":
[]},
{"block":1115621,"size":0,"storage":
[]},
{"block":1115622,"size":0,"storage":
[]},
{"block":1115623,"size":0,"storage":
[]},
{"block":1115624,"size":0,"storage":
[]},
{"block":1115625,"size":0,"storage":
[]},
{"block":1115626,"size":0,"storage":
[]},
{"block":1115627,"size":0,"storage":
[]},
{"block":1115628,"size":0,"storage":
[]},
{"block":1115629,"size":0,"storage":
[]},
{"block":1115630,"size":0,"storage":
[]},
{"block":1115631,"size":0,"storage":
[]},
{"block":1115632,"size":0,"storage":
[]},
{"block":1115633,"size":0,"storage":
[]},
{"block":1115634,"size":0,"storage":
[]},
{"block":1115635,"size":0,"storage":
[]},
{"block":1115636,"size":0,"storage":
[]},
{"block":1115637,"size":0,"storage":
[]},
{"block":1115638,"size":0,"storage":
[]},
{"block":1115639,"size":0,"storage":
[]},
{"block":1115640,"size":0,"storage":
[]},
{"block":1115641,"size":0,"storage":
[]},
{"block":1115642,"size":0,"storage":
[]},
{"block":1115643,"size":0,"storage":
[]},
{"block":1115644,"size":0,"storage":
[]},
{"block":1115645,"size":0,"storage":
[]},
{"block":1115646,"size":0,"storage":
[]},
{"block":1115647,"size":0,"storage":
[]},
{"block":1115648,"size":0,"storage":
[]},
{"block":1115649,"size":0,"storage":
[]},
{"block":1115650,"size":0,"storage":
[]},
{"block":1115651,"size":0,"storage":
[]},
{"block":1115652,"size":0,"storage":
[]},
{"block":1115653,"size":0,"storage":
[]},
{"block":1115654,"size":0,"storage":
[]},
{"block":1115655,"size":0,"storage":
[]},
{"block":1115656,"size":0,"storage":
[]},
{"block":1115657,"size":0,"storage":
[]},
{"block":1115658,"size":0,"storage":
[]},
{"block":1115659,"size":0,"storage":
[]},
{"block":1115660,"size":0,"storage":
[]},
{"block":1115661,"size":0,"storage":
[]},
{"block":1115662,"size":0,"storage":
[]},
{"block":1115663,"size":0,"storage":
[]},
{"block":1115664,"size":0,"storage":
[]},
{"block":1115665,"size":0,"storage":
[]},
{"block":1115666,"size":0,"storage":
[]},
{"block":1115667,"size":0,"storage":
[]},
{"block":1115668,"size":0,"storage":
[]},
{"block":1115669,"size":0,"storage":
[]},
{"block":1115670,"size":0,"storage":
[]},
{"block":1115671,"size":0,"storage":
[]},
{"block":1115672,"size":0,"storage":
[]},
{"block":1115673,"size":0,"storage":
[]},
{"block":1115674,"size":0,"storage":
[]},
{"block":1115675,"size":0,"storage":
[]},
{"block":1115676,"size":0,"storage":
[]},
{"block":1115677,"size":0,"storage":
[]},
{"block":1115678,"size":0,"storage":
[]},
{"block":1115679,"size":0,"storage":
[]},
{"block":1115680,"size":0,"storage":
[]},
{"block":1115681,"size":0,"storage":
[]},
{"block":1115682,"size":0,"storage":
[]},
{"block":1115683,"size":0,"storage":
[]},
{"block":1115684,"size":0,"storage":
[]},
{"block":1115685,"size":0,"storage":
[]},
{"block":1115686,"size":0,"storage":
[]},
{"block":1115687,"size":0,"storage":
[]},
{"block":1115688,"size":0,"storage":
[]},
{"block":1115689,"size":0,"storage":
[]},
{"block":1115690,"size":0,"storage":
[]},
{"block":1115691,"size":0,"storage":
[]},
{"block":1115692,"size":0,"storage":
[]},
{"block":1115693,"size":0,"storage":
[]},
{"block":1115694,"size":0,"storage":
[]},
{"block":1115695,"size":0,"storage":
[]},
{"block":1115696,"size":0,"storage":
[]},
{"block":1115697,"size":0,"storage":
[]},
{"block":1115698,"size":0,"storage":
[]},
{"block":1115699,"size":0,"storage":
[]},
{"block":1115700,"size":0,"storage":
[]},
{"block":1115701,"size":0,"storage":
[]},
{"block":1115702,"size":0,"storage":
[]},
{"block":1115703,"size":0,"storage":
[]},
{"block":1115704,"size":0,"storage":
[]},
{"block":1115705,"size":0,"storage":
[]},
{"block":1115706,"size":0,"storage":
[]},
{"block":1115707,"size":0,"storage":
[]},
{"block":1115708,"size":0,"storage":
[]},
{"block":1115709,"size":0,"storage":
[]},
{"block":1115710,"size":0,"storage":
[]},
{"block":1115711,"size":0,"storage":
[]},
{"block":1115712,"size":0,"storage":
[]},
{"block":1115713,"size":0,"storage":
[]},
{"block":1115714,"size":0,"storage":
[]},
{"block":1115715,"size":0,"storage":
[]},
{"block":1115716,"size":0,"storage":
[]},
{"block":1115717,"size":0,"storage":
[]},
{"block":1115718,"size":0,"storage":
[]},
{"block":1115719,"size":0,"storage":
[]},
{"block":1115720,"size":0,"storage":
[]},
{"block":1115721,"size":0,"storage":
[]},
{"block":1115722,"size":0,"storage":
[]},
{"block":1115723,"size":0,"storage":
[]},
{"block":1115724,"size":0,"storage":
[]},
{"block":1115725,"size":0,"storage":
[]},
{"block":1115726,"size":0,"storage":
[]},
{"block":1115727,"size":0,"storage":
[]},
{"block":1115728,"size":0,"storage":
[]},
{"block":1115729,"size":0,"storage":
[]},
{"block":1115730,"size":0,"storage":
[]},
{"block":1115731,"size":0,"storage":
[]},
{"block":1115732,"size":0,"storage":
[]},
{"block":1115733,"size":0,"storage":
[]},
{"block":1115734,"size":0,"storage":
[]},
{"block":1115735,"size":0,"storage":
[]},
{"block":1115736,"size":0,"storage":
[]},
{"block":1115737,"size":0,"storage":
[]},
{"block":1115738,"size":0,"storage":
[]},
{"block":1115739,"size":0,"storage":
[]},
{"block":1115740,"size":0,"storage":
[]},
{"block":1115741,"size":0,"storage":
[]},
{"block":1115742,"size":0,"storage":
[]},
{"block":1115743,"size":0,"storage":
[]},
{"block":1115744,"size":0,"storage":
[]},
{"block":1115745,"size":0,"storage":
[]},
{"block":1115746,"size":0,"storage":
[]},
{"block":1115747,"size":0,"storage":
[]},
{"block":1115748,"size":0,"storage":
[]},
{"block":1115749,"size":0,"storage":
[]},
{"block":1115750,"size":0,"storage":
[]},
{"block":1115751,"size":0,"storage":
[]},
{"block":1115752,"size":0,"storage":
[]},
{"block":1115753,"size":0,"storage":
[]},
{"block":1115754,"size":0,"storage":
[]},
{"block":1115755,"size":0,"storage":
[]},
{"block":1115756,"size":0,"storage":
[]},
{"block":1115757,"size":0,"storage":
[]},
{"block":1115758,"size":0,"storage":
[]},
{"block":1115759,"size":0,"storage":
[]},
{"block":1115760,"size":0,"storage":
[]},
{"block":1115761,"size":0,"storage":
[]},
{"block":1115762,"size":0,"storage":
[]},
{"block":1115763,"size":0,"storage":
[]},
{"block":1115764,"size":0,"storage":
[]},
{"block":1115765,"size":0,"storage":
[]},
{"block":1115766,"size":0,"storage":
[]},
{"block":1115767,"size":0,"storage":
[]},
{"block":1115768,"size":0,"storage":
[]},
{"block":1115769,"size":0,"storage":
[]},
{"block":1115770,"size":0,"storage":
[]},
{"block":1115771,"size":0,"storage":
[]},
{"block":1115772,"size":0,"storage":
[]},
{"block":1115773,"size":0,"storage":
[]},
{"block":1115774,"size":0,"storage":
[]},
{"block":1115775,"size":0,"storage":
[]},
{"block":1115776,"size":0,"storage":
[]},
{"block":1115777,"size":0,"storage":
[]},
{"block":1115778,"size":0,"storage":
[]},
{"block":1115779,"size":0,"storage":
[]},
{"block":1115780,"size":0,"storage":
[]},
{"block":1115781,"size":0,"storage":
[]},
{"block":1115782,"size":0,"storage":
[]},
{"block":1115783,"size":0,"storage":
[]},
{"block":1115784,"size":0,"storage":
[]},
{"block":1115785,"size":0,"storage":
[]},
{"block":1115786,"size":0,"storage":
[]},
{"block":1115787,"size":0,"storage":
[]},
{"block":1115788,"size":0,"storage":
[]},
{"block":1115789,"size":0,"storage":
[]},
{"block":1115790,"size":0,"storage":
[]},
{"block":1115791,"size":0,"storage":
[]},
{"block":1115792,"size":0,"storage":
[]},
{"block":1115793,"size":0,"storage":
[]},
{"block":1115794,"size":0,"storage":
[]},
{"block":1115795,"size":0,"storage":
[]},
{"block":1115796,"size":0,"storage":
[]},
{"block":1115797,"size":0,"storage":
[]},
{"block":1115798,"size":0,"storage":
[]},
{"block":1115799,"size":0,"storage":
[]},
{"block":1115800,"size":0,"storage":
[]},
{"block":1115801,"size":0,"storage":
[]},
{"block":1115802,"size":0,"storage":
[]},
{"block":1115803,"size":0,"storage":
[]},
{"block":1115804,"size":0,"storage":
[]},
{"block":1115805,"size":0,"storage":
[]},
{"block":1115806,"size":0,"storage":
[]},
{"block":1115807,"size":0,"storage":
[]},
{"block":1115808,"size":0,"storage":
[]},
{"block":1115809,"size":0,"storage":
[]},
{"block":1115810,"size":0,"storage":
[]},
{"block":1115811,"size":0,"storage":
[]},
{"block":1115812,"size":0,"storage":
[]},
{"block":1115813,"size":0,"storage":
[]},
{"block":1115814,"size":0,"storage":
[]},
{"block":1115815,"size":0,"storage":
[]},
{"block":1115816,"size":0,"storage":
[]},
{"block":1115817,"size":0,"storage":
[]},
{"block":1115818,"size":0,"storage":
[]},
{"block":1115819,"size":0,"storage":
[]},
{"block":1115820,"size":0,"storage":
[]},
{"block":1115821,"size":0,"storage":
[]},
{"block":1115822,"size":0,"storage":
[]},
{"block":1115823,"size":0,"storage":
[]},
{"block":1115824,"size":0,"storage":
[]},
{"block":1115825,"size":0,"storage":
[]},
{"block":1115826,"size":0,"storage":
[]},
{"block":1115827,"size":0,"storage":
[]},
{"block":1115828,"size":0,"storage":
[]},
{"block":1115829,"size":0,"storage":
[]},
{"block":1115830,"size":0,"storage":
[]},
{"block":1115831,"size":0,"storage":
[]},
{"block":1115832,"size":0,"storage":
[]},
{"block":1115833,"size":0,"storage":
[]},
{"block":1115834,"size":0,"storage":
[]},
{"block":1115835,"size":0,"storage":
[]},
{"block":1115836,"size":0,"storage":
[]},
{"block":1115837,"size":0,"storage":
[]},
{"block":1115838,"size":0,"storage":
[]},
{"block":1115839,"size":0,"storage":
[]},
{"block":1115840,"size":0,"storage":
[]},
{"block":1115841,"size":0,"storage":
[]},
{"block":1115842,"size":0,"storage":
[]},
{"block":1115843,"size":0,"storage":
[]},
{"block":1115844,"size":0,"storage":
[]},
{"block":1115845,"size":0,"storage":
[]},
{"block":1115846,"size":0,"storage":
[]},
{"block":1115847,"size":0,"storage":
[]},
{"block":1115848,"size":0,"storage":
[]},
{"block":1115849,"size":0,"storage":
[]},
{"block":1115850,"size":0,"storage":
[]},
{"block":1115851,"size":0,"storage":
[]},
{"block":1115852,"size":0,"storage":
[]},
{"block":1115853,"size":0,"storage":
[]},
{"block":1115854,"size":0,"storage":
[]},
{"block":1115855,"size":0,"storage":
[]},
{"block":1115856,"size":0,"storage":
[]},
{"block":1115857,"size":0,"storage":
[]},
{"block":1115858,"size":0,"storage":
[]},
{"block":1115859,"size":0,"storage":
[]},
{"block":1115860,"size":0,"storage":
[]},
{"block":1115861,"size":0,"storage":
[]},
{"block":1115862,"size":0,"storage":
[]},
{"block":1115863,"size":0,"storage":
[]},
{"block":1115864,"size":0,"storage":
[]},
{"block":1115865,"size":0,"storage":
[]},
{"block":1115866,"size":0,"storage":
[]},
{"block":1115867,"size":0,"storage":
[]},
{"block":1115868,"size":0,"storage":
[]},
{"block":1115869,"size":0,"storage":
[]},
{"block":1115870,"size":0,"storage":
[]},
{"block":1115871,"size":0,"storage":
[]},
{"block":1115872,"size":0,"storage":
[]},
{"block":1115873,"size":0,"storage":
[]},
{"block":1115874,"size":0,"storage":
[]},
{"block":1115875,"size":0,"storage":
[]},
{"block":1115876,"size":0,"storage":
[]},
{"block":1115877,"size":0,"storage":
[]},
{"block":1115878,"size":0,"storage":
[]},
{"block":1115879,"size":0,"storage":
[]},
{"block":1115880,"size":0,"storage":
[]},
{"block":1115881,"size":0,"storage":
[]},
{"block":1115882,"size":0,"storage":
[]},
{"block":1115883,"size":0,"storage":
[]},
{"block":1115884,"size":0,"storage":
[]},
{"block":1115885,"size":0,"storage":
[]},
{"block":1115886,"size":0,"storage":
[]},
{"block":1115887,"size":0,"storage":
[]},
{"block":1115888,"size":0,"storage":
[]},
{"block":1115889,"size":0,"storage":
[]},
{"block":1115890,"size":0,"storage":
[]},
{"block":1115891,"size":0,"storage":
[]},
{"block":1115892,"size":0,"storage":
[]},
{"block":1115893,"size":0,"storage":
[]},
{"block":1115894,"size":0,"storage":
[]},
{"block":1115895,"size":0,"storage":
[]},
{"block":1115896,"size":0,"storage":
[]},
{"block":1115897,"size":0,"storage":
[]},
{"block":1115898,"size":0,"storage":
[]},
{"block":1115899,"size":0,"storage":
[]},
{"block":1115900,"size":0,"storage":
[]},
{"block":1115901,"size":0,"storage":
[]},
{"block":1115902,"size":0,"storage":
[]},
{"block":1115903,"size":0,"storage":
[]},
{"block":1115904,"size":0,"storage":
[]},
{"block":1115905,"size":0,"storage":
[]},
{"block":1115906,"size":0,"storage":
[]},
{"block":1115907,"size":0,"storage":
[]},
{"block":1115908,"size":0,"storage":
[]},
{"block":1115909,"size":0,"storage":
[]},
{"block":1115910,"size":0,"storage":
[]},
{"block":1115911,"size":0,"storage":
[]},
{"block":1115912,"size":0,"storage":
[]},
{"block":1115913,"size":0,"storage":
[]},
{"block":1115914,"size":0,"storage":
[]},
{"block":1115915,"size":0,"storage":
[]},
{"block":1115916,"size":0,"storage":
[]},
{"block":1115917,"size":0,"storage":
[]},
{"block":1115918,"size":0,"storage":
[]},
{"block":1115919,"size":0,"storage":
[]},
{"block":1115920,"size":0,"storage":
[]},
{"block":1115921,"size":0,"storage":
[]},
{"block":1115922,"size":0,"storage":
[]},
{"block":1115923,"size":0,"storage":
[]},
{"block":1115924,"size":0,"storage":
[]},
{"block":1115925,"size":0,"storage":
[]},
{"block":1115926,"size":0,"storage":
[]},
{"block":1115927,"size":0,"storage":
[]},
{"block":1115928,"size":0,"storage":
[]},
{"block":1115929,"size":0,"storage":
[]},
{"block":1115930,"size":0,"storage":
[]},
{"block":1115931,"size":0,"storage":
[]},
{"block":1115932,"size":0,"storage":
[]},
{"block":1115933,"size":0,"storage":
[]},
{"block":1115934,"size":0,"storage":
[]},
{"block":1115935,"size":0,"storage":
[]},
{"block":1115936,"size":0,"storage":
[]},
{"block":1115937,"size":0,"storage":
[]},
{"block":1115938,"size":0,"storage":
[]},
{"block":1115939,"size":0,"storage":
[]},
{"block":1115940,"size":0,"storage":
[]},
{"block":1115941,"size":0,"storage":
[]},
{"block":1115942,"size":0,"storage":
[]},
{"block":1115943,"size":0,"storage":
[]},
{"block":1115944,"size":0,"storage":
[]},
{"block":1115945,"size":0,"storage":
[]},
{"block":1115946,"size":0,"storage":
[]},
{"block":1115947,"size":0,"storage":
[]},
{"block":1115948,"size":0,"storage":
[]},
{"block":1115949,"size":0,"storage":
[]},
{"block":1115950,"size":0,"storage":
[]},
{"block":1115951,"size":0,"storage":
[]},
{"block":1115952,"size":0,"storage":
[]},
{"block":1115953,"size":0,"storage":
[]},
{"block":1115954,"size":0,"storage":
[]},
{"block":1115955,"size":0,"storage":
[]},
{"block":1115956,"size":0,"storage":
[]},
{"block":1115957,"size":0,"storage":
[]},
{"block":1115958,"size":0,"storage":
[]},
{"block":1115959,"size":0,"storage":
[]},
{"block":1115960,"size":0,"storage":
[]},
{"block":1115961,"size":0,"storage":
[]},
{"block":1115962,"size":0,"storage":
[]},
{"block":1115963,"size":0,"storage":
[]},
{"block":1115964,"size":0,"storage":
[]},
{"block":1115965,"size":0,"storage":
[]},
{"block":1115966,"size":0,"storage":
[]},
{"block":1115967,"size":0,"storage":
[]},
{"block":1115968,"size":0,"storage":
[]},
{"block":1115969,"size":0,"storage":
[]},
{"block":1115970,"size":0,"storage":
[]},
{"block":1115971,"size":0,"storage":
[]},
{"block":1115972,"size":0,"storage":
[]},
{"block":1115973,"size":0,"storage":
[]},
{"block":1115974,"size":0,"storage":
[]},
{"block":1115975,"size":0,"storage":
[]},
{"block":1115976,"size":0,"storage":
[]},
{"block":1115977,"size":0,"storage":
[]},
{"block":1115978,"size":0,"storage":
[]},
{"block":1115979,"size":0,"storage":
[]},
{"block":1115980,"size":0,"storage":
[]},
{"block":1115981,"size":0,"storage":
[]},
{"block":1115982,"size":0,"storage":
[]},
{"block":1115983,"size":0,"storage":
[]},
{"block":1115984,"size":0,"storage":
[]},
{"block":1115985,"size":0,"storage":
[]},
{"block":1115986,"size":0,"storage":
[]},
{"block":1115987,"size":0,"storage":
[]},
{"block":1115988,"size":0,"storage":
[]},
{"block":1115989,"size":0,"storage":
[]},
{"block":1115990,"size":0,"storage":
[]},
{"block":1115991,"size":0,"storage":
[]},
{"block":1115992,"size":0,"storage":
[]},
{"block":1115993,"size":0,"storage":
[]},
{"block":1115994,"size":0,"storage":
[]},
{"block":1115995,"size":0,"storage":
[]},
{"block":1115996,"size":0,"storage":
[]},
{"block":1115997,"size":0,"storage":
[]},
{"block":1115998,"size":0,"storage":
[]},
{"block":1115999,"size":0,"storage":
[]},
{"block":1116000,"size":0,"storage":
[]},
]