[{"block":786001,"size":0,"storage":
[]},
{"block":786002,"size":0,"storage":
[]},
{"block":786003,"size":0,"storage":
[]},
{"block":786004,"size":0,"storage":
[]},
{"block":786005,"size":0,"storage":
[]},
{"block":786006,"size":0,"storage":
[]},
{"block":786007,"size":0,"storage":
[]},
{"block":786008,"size":0,"storage":
[]},
{"block":786009,"size":0,"storage":
[]},
{"block":786010,"size":0,"storage":
[]},
{"block":786011,"size":0,"storage":
[]},
{"block":786012,"size":0,"storage":
[]},
{"block":786013,"size":0,"storage":
[]},
{"block":786014,"size":0,"storage":
[]},
{"block":786015,"size":0,"storage":
[]},
{"block":786016,"size":0,"storage":
[]},
{"block":786017,"size":0,"storage":
[]},
{"block":786018,"size":0,"storage":
[]},
{"block":786019,"size":0,"storage":
[]},
{"block":786020,"size":0,"storage":
[]},
{"block":786021,"size":0,"storage":
[]},
{"block":786022,"size":0,"storage":
[]},
{"block":786023,"size":0,"storage":
[]},
{"block":786024,"size":0,"storage":
[]},
{"block":786025,"size":0,"storage":
[]},
{"block":786026,"size":0,"storage":
[]},
{"block":786027,"size":0,"storage":
[]},
{"block":786028,"size":0,"storage":
[]},
{"block":786029,"size":0,"storage":
[]},
{"block":786030,"size":0,"storage":
[]},
{"block":786031,"size":0,"storage":
[]},
{"block":786032,"size":0,"storage":
[]},
{"block":786033,"size":0,"storage":
[]},
{"block":786034,"size":0,"storage":
[]},
{"block":786035,"size":0,"storage":
[]},
{"block":786036,"size":0,"storage":
[]},
{"block":786037,"size":0,"storage":
[]},
{"block":786038,"size":0,"storage":
[]},
{"block":786039,"size":0,"storage":
[]},
{"block":786040,"size":0,"storage":
[]},
{"block":786041,"size":0,"storage":
[]},
{"block":786042,"size":0,"storage":
[]},
{"block":786043,"size":0,"storage":
[]},
{"block":786044,"size":0,"storage":
[]},
{"block":786045,"size":0,"storage":
[]},
{"block":786046,"size":0,"storage":
[]},
{"block":786047,"size":0,"storage":
[]},
{"block":786048,"size":0,"storage":
[]},
{"block":786049,"size":0,"storage":
[]},
{"block":786050,"size":0,"storage":
[]},
{"block":786051,"size":0,"storage":
[]},
{"block":786052,"size":0,"storage":
[]},
{"block":786053,"size":0,"storage":
[]},
{"block":786054,"size":0,"storage":
[]},
{"block":786055,"size":0,"storage":
[]},
{"block":786056,"size":0,"storage":
[]},
{"block":786057,"size":0,"storage":
[]},
{"block":786058,"size":0,"storage":
[]},
{"block":786059,"size":0,"storage":
[]},
{"block":786060,"size":0,"storage":
[]},
{"block":786061,"size":0,"storage":
[]},
{"block":786062,"size":0,"storage":
[]},
{"block":786063,"size":0,"storage":
[]},
{"block":786064,"size":0,"storage":
[]},
{"block":786065,"size":0,"storage":
[]},
{"block":786066,"size":0,"storage":
[]},
{"block":786067,"size":0,"storage":
[]},
{"block":786068,"size":0,"storage":
[]},
{"block":786069,"size":0,"storage":
[]},
{"block":786070,"size":0,"storage":
[]},
{"block":786071,"size":0,"storage":
[]},
{"block":786072,"size":0,"storage":
[]},
{"block":786073,"size":0,"storage":
[]},
{"block":786074,"size":0,"storage":
[]},
{"block":786075,"size":0,"storage":
[]},
{"block":786076,"size":0,"storage":
[]},
{"block":786077,"size":0,"storage":
[]},
{"block":786078,"size":0,"storage":
[]},
{"block":786079,"size":0,"storage":
[]},
{"block":786080,"size":0,"storage":
[]},
{"block":786081,"size":0,"storage":
[]},
{"block":786082,"size":0,"storage":
[]},
{"block":786083,"size":0,"storage":
[]},
{"block":786084,"size":0,"storage":
[]},
{"block":786085,"size":0,"storage":
[]},
{"block":786086,"size":0,"storage":
[]},
{"block":786087,"size":0,"storage":
[]},
{"block":786088,"size":0,"storage":
[]},
{"block":786089,"size":0,"storage":
[]},
{"block":786090,"size":0,"storage":
[]},
{"block":786091,"size":0,"storage":
[]},
{"block":786092,"size":0,"storage":
[]},
{"block":786093,"size":0,"storage":
[]},
{"block":786094,"size":0,"storage":
[]},
{"block":786095,"size":0,"storage":
[]},
{"block":786096,"size":0,"storage":
[]},
{"block":786097,"size":0,"storage":
[]},
{"block":786098,"size":0,"storage":
[]},
{"block":786099,"size":0,"storage":
[]},
{"block":786100,"size":0,"storage":
[]},
{"block":786101,"size":0,"storage":
[]},
{"block":786102,"size":0,"storage":
[]},
{"block":786103,"size":0,"storage":
[]},
{"block":786104,"size":0,"storage":
[]},
{"block":786105,"size":0,"storage":
[]},
{"block":786106,"size":0,"storage":
[]},
{"block":786107,"size":0,"storage":
[]},
{"block":786108,"size":0,"storage":
[]},
{"block":786109,"size":0,"storage":
[]},
{"block":786110,"size":0,"storage":
[]},
{"block":786111,"size":0,"storage":
[]},
{"block":786112,"size":0,"storage":
[]},
{"block":786113,"size":0,"storage":
[]},
{"block":786114,"size":0,"storage":
[]},
{"block":786115,"size":0,"storage":
[]},
{"block":786116,"size":0,"storage":
[]},
{"block":786117,"size":0,"storage":
[]},
{"block":786118,"size":0,"storage":
[]},
{"block":786119,"size":0,"storage":
[]},
{"block":786120,"size":0,"storage":
[]},
{"block":786121,"size":0,"storage":
[]},
{"block":786122,"size":0,"storage":
[]},
{"block":786123,"size":0,"storage":
[]},
{"block":786124,"size":0,"storage":
[]},
{"block":786125,"size":0,"storage":
[]},
{"block":786126,"size":0,"storage":
[]},
{"block":786127,"size":0,"storage":
[]},
{"block":786128,"size":0,"storage":
[]},
{"block":786129,"size":0,"storage":
[]},
{"block":786130,"size":0,"storage":
[]},
{"block":786131,"size":0,"storage":
[]},
{"block":786132,"size":0,"storage":
[]},
{"block":786133,"size":0,"storage":
[]},
{"block":786134,"size":0,"storage":
[]},
{"block":786135,"size":0,"storage":
[]},
{"block":786136,"size":0,"storage":
[]},
{"block":786137,"size":0,"storage":
[]},
{"block":786138,"size":0,"storage":
[]},
{"block":786139,"size":0,"storage":
[]},
{"block":786140,"size":0,"storage":
[]},
{"block":786141,"size":0,"storage":
[]},
{"block":786142,"size":0,"storage":
[]},
{"block":786143,"size":0,"storage":
[]},
{"block":786144,"size":0,"storage":
[]},
{"block":786145,"size":0,"storage":
[]},
{"block":786146,"size":0,"storage":
[]},
{"block":786147,"size":0,"storage":
[]},
{"block":786148,"size":0,"storage":
[]},
{"block":786149,"size":0,"storage":
[]},
{"block":786150,"size":0,"storage":
[]},
{"block":786151,"size":0,"storage":
[]},
{"block":786152,"size":0,"storage":
[]},
{"block":786153,"size":0,"storage":
[]},
{"block":786154,"size":0,"storage":
[]},
{"block":786155,"size":0,"storage":
[]},
{"block":786156,"size":0,"storage":
[]},
{"block":786157,"size":0,"storage":
[]},
{"block":786158,"size":0,"storage":
[]},
{"block":786159,"size":0,"storage":
[]},
{"block":786160,"size":0,"storage":
[]},
{"block":786161,"size":0,"storage":
[]},
{"block":786162,"size":0,"storage":
[]},
{"block":786163,"size":0,"storage":
[]},
{"block":786164,"size":0,"storage":
[]},
{"block":786165,"size":0,"storage":
[]},
{"block":786166,"size":0,"storage":
[]},
{"block":786167,"size":0,"storage":
[]},
{"block":786168,"size":0,"storage":
[]},
{"block":786169,"size":0,"storage":
[]},
{"block":786170,"size":0,"storage":
[]},
{"block":786171,"size":0,"storage":
[]},
{"block":786172,"size":0,"storage":
[]},
{"block":786173,"size":0,"storage":
[]},
{"block":786174,"size":0,"storage":
[]},
{"block":786175,"size":0,"storage":
[]},
{"block":786176,"size":0,"storage":
[]},
{"block":786177,"size":0,"storage":
[]},
{"block":786178,"size":0,"storage":
[]},
{"block":786179,"size":0,"storage":
[]},
{"block":786180,"size":0,"storage":
[]},
{"block":786181,"size":0,"storage":
[]},
{"block":786182,"size":0,"storage":
[]},
{"block":786183,"size":0,"storage":
[]},
{"block":786184,"size":0,"storage":
[]},
{"block":786185,"size":0,"storage":
[]},
{"block":786186,"size":0,"storage":
[]},
{"block":786187,"size":0,"storage":
[]},
{"block":786188,"size":0,"storage":
[]},
{"block":786189,"size":0,"storage":
[]},
{"block":786190,"size":0,"storage":
[]},
{"block":786191,"size":0,"storage":
[]},
{"block":786192,"size":0,"storage":
[]},
{"block":786193,"size":0,"storage":
[]},
{"block":786194,"size":0,"storage":
[]},
{"block":786195,"size":0,"storage":
[]},
{"block":786196,"size":0,"storage":
[]},
{"block":786197,"size":0,"storage":
[]},
{"block":786198,"size":0,"storage":
[]},
{"block":786199,"size":0,"storage":
[]},
{"block":786200,"size":0,"storage":
[]},
{"block":786201,"size":0,"storage":
[]},
{"block":786202,"size":0,"storage":
[]},
{"block":786203,"size":0,"storage":
[]},
{"block":786204,"size":0,"storage":
[]},
{"block":786205,"size":0,"storage":
[]},
{"block":786206,"size":0,"storage":
[]},
{"block":786207,"size":0,"storage":
[]},
{"block":786208,"size":0,"storage":
[]},
{"block":786209,"size":0,"storage":
[]},
{"block":786210,"size":0,"storage":
[]},
{"block":786211,"size":0,"storage":
[]},
{"block":786212,"size":0,"storage":
[]},
{"block":786213,"size":0,"storage":
[]},
{"block":786214,"size":0,"storage":
[]},
{"block":786215,"size":0,"storage":
[]},
{"block":786216,"size":0,"storage":
[]},
{"block":786217,"size":0,"storage":
[]},
{"block":786218,"size":0,"storage":
[]},
{"block":786219,"size":0,"storage":
[]},
{"block":786220,"size":0,"storage":
[]},
{"block":786221,"size":0,"storage":
[]},
{"block":786222,"size":0,"storage":
[]},
{"block":786223,"size":0,"storage":
[]},
{"block":786224,"size":0,"storage":
[]},
{"block":786225,"size":0,"storage":
[]},
{"block":786226,"size":0,"storage":
[]},
{"block":786227,"size":0,"storage":
[]},
{"block":786228,"size":0,"storage":
[]},
{"block":786229,"size":0,"storage":
[]},
{"block":786230,"size":0,"storage":
[]},
{"block":786231,"size":0,"storage":
[]},
{"block":786232,"size":0,"storage":
[]},
{"block":786233,"size":0,"storage":
[]},
{"block":786234,"size":0,"storage":
[]},
{"block":786235,"size":0,"storage":
[]},
{"block":786236,"size":0,"storage":
[]},
{"block":786237,"size":0,"storage":
[]},
{"block":786238,"size":0,"storage":
[]},
{"block":786239,"size":0,"storage":
[]},
{"block":786240,"size":0,"storage":
[]},
{"block":786241,"size":0,"storage":
[]},
{"block":786242,"size":0,"storage":
[]},
{"block":786243,"size":0,"storage":
[]},
{"block":786244,"size":0,"storage":
[]},
{"block":786245,"size":0,"storage":
[]},
{"block":786246,"size":0,"storage":
[]},
{"block":786247,"size":0,"storage":
[]},
{"block":786248,"size":0,"storage":
[]},
{"block":786249,"size":0,"storage":
[]},
{"block":786250,"size":0,"storage":
[]},
{"block":786251,"size":0,"storage":
[]},
{"block":786252,"size":0,"storage":
[]},
{"block":786253,"size":0,"storage":
[]},
{"block":786254,"size":0,"storage":
[]},
{"block":786255,"size":0,"storage":
[]},
{"block":786256,"size":0,"storage":
[]},
{"block":786257,"size":0,"storage":
[]},
{"block":786258,"size":0,"storage":
[]},
{"block":786259,"size":0,"storage":
[]},
{"block":786260,"size":0,"storage":
[]},
{"block":786261,"size":0,"storage":
[]},
{"block":786262,"size":0,"storage":
[]},
{"block":786263,"size":0,"storage":
[]},
{"block":786264,"size":0,"storage":
[]},
{"block":786265,"size":0,"storage":
[]},
{"block":786266,"size":0,"storage":
[]},
{"block":786267,"size":0,"storage":
[]},
{"block":786268,"size":0,"storage":
[]},
{"block":786269,"size":0,"storage":
[]},
{"block":786270,"size":0,"storage":
[]},
{"block":786271,"size":0,"storage":
[]},
{"block":786272,"size":0,"storage":
[]},
{"block":786273,"size":0,"storage":
[]},
{"block":786274,"size":0,"storage":
[]},
{"block":786275,"size":0,"storage":
[]},
{"block":786276,"size":0,"storage":
[]},
{"block":786277,"size":0,"storage":
[]},
{"block":786278,"size":0,"storage":
[]},
{"block":786279,"size":0,"storage":
[]},
{"block":786280,"size":0,"storage":
[]},
{"block":786281,"size":0,"storage":
[]},
{"block":786282,"size":0,"storage":
[]},
{"block":786283,"size":0,"storage":
[]},
{"block":786284,"size":0,"storage":
[]},
{"block":786285,"size":0,"storage":
[]},
{"block":786286,"size":0,"storage":
[]},
{"block":786287,"size":0,"storage":
[]},
{"block":786288,"size":0,"storage":
[]},
{"block":786289,"size":0,"storage":
[]},
{"block":786290,"size":0,"storage":
[]},
{"block":786291,"size":0,"storage":
[]},
{"block":786292,"size":0,"storage":
[]},
{"block":786293,"size":0,"storage":
[]},
{"block":786294,"size":0,"storage":
[]},
{"block":786295,"size":0,"storage":
[]},
{"block":786296,"size":0,"storage":
[]},
{"block":786297,"size":0,"storage":
[]},
{"block":786298,"size":0,"storage":
[]},
{"block":786299,"size":0,"storage":
[]},
{"block":786300,"size":0,"storage":
[]},
{"block":786301,"size":0,"storage":
[]},
{"block":786302,"size":0,"storage":
[]},
{"block":786303,"size":0,"storage":
[]},
{"block":786304,"size":0,"storage":
[]},
{"block":786305,"size":0,"storage":
[]},
{"block":786306,"size":0,"storage":
[]},
{"block":786307,"size":0,"storage":
[]},
{"block":786308,"size":0,"storage":
[]},
{"block":786309,"size":0,"storage":
[]},
{"block":786310,"size":0,"storage":
[]},
{"block":786311,"size":0,"storage":
[]},
{"block":786312,"size":0,"storage":
[]},
{"block":786313,"size":0,"storage":
[]},
{"block":786314,"size":0,"storage":
[]},
{"block":786315,"size":0,"storage":
[]},
{"block":786316,"size":0,"storage":
[]},
{"block":786317,"size":0,"storage":
[]},
{"block":786318,"size":0,"storage":
[]},
{"block":786319,"size":0,"storage":
[]},
{"block":786320,"size":0,"storage":
[]},
{"block":786321,"size":0,"storage":
[]},
{"block":786322,"size":0,"storage":
[]},
{"block":786323,"size":0,"storage":
[]},
{"block":786324,"size":0,"storage":
[]},
{"block":786325,"size":0,"storage":
[]},
{"block":786326,"size":0,"storage":
[]},
{"block":786327,"size":0,"storage":
[]},
{"block":786328,"size":0,"storage":
[]},
{"block":786329,"size":0,"storage":
[]},
{"block":786330,"size":0,"storage":
[]},
{"block":786331,"size":0,"storage":
[]},
{"block":786332,"size":0,"storage":
[]},
{"block":786333,"size":0,"storage":
[]},
{"block":786334,"size":0,"storage":
[]},
{"block":786335,"size":0,"storage":
[]},
{"block":786336,"size":0,"storage":
[]},
{"block":786337,"size":0,"storage":
[]},
{"block":786338,"size":0,"storage":
[]},
{"block":786339,"size":0,"storage":
[]},
{"block":786340,"size":0,"storage":
[]},
{"block":786341,"size":0,"storage":
[]},
{"block":786342,"size":0,"storage":
[]},
{"block":786343,"size":0,"storage":
[]},
{"block":786344,"size":0,"storage":
[]},
{"block":786345,"size":0,"storage":
[]},
{"block":786346,"size":0,"storage":
[]},
{"block":786347,"size":0,"storage":
[]},
{"block":786348,"size":0,"storage":
[]},
{"block":786349,"size":0,"storage":
[]},
{"block":786350,"size":0,"storage":
[]},
{"block":786351,"size":0,"storage":
[]},
{"block":786352,"size":0,"storage":
[]},
{"block":786353,"size":0,"storage":
[]},
{"block":786354,"size":0,"storage":
[]},
{"block":786355,"size":0,"storage":
[]},
{"block":786356,"size":0,"storage":
[]},
{"block":786357,"size":0,"storage":
[]},
{"block":786358,"size":0,"storage":
[]},
{"block":786359,"size":0,"storage":
[]},
{"block":786360,"size":0,"storage":
[]},
{"block":786361,"size":0,"storage":
[]},
{"block":786362,"size":0,"storage":
[]},
{"block":786363,"size":0,"storage":
[]},
{"block":786364,"size":0,"storage":
[]},
{"block":786365,"size":0,"storage":
[]},
{"block":786366,"size":0,"storage":
[]},
{"block":786367,"size":0,"storage":
[]},
{"block":786368,"size":0,"storage":
[]},
{"block":786369,"size":0,"storage":
[]},
{"block":786370,"size":0,"storage":
[]},
{"block":786371,"size":0,"storage":
[]},
{"block":786372,"size":0,"storage":
[]},
{"block":786373,"size":0,"storage":
[]},
{"block":786374,"size":0,"storage":
[]},
{"block":786375,"size":0,"storage":
[]},
{"block":786376,"size":0,"storage":
[]},
{"block":786377,"size":0,"storage":
[]},
{"block":786378,"size":0,"storage":
[]},
{"block":786379,"size":0,"storage":
[]},
{"block":786380,"size":0,"storage":
[]},
{"block":786381,"size":0,"storage":
[]},
{"block":786382,"size":0,"storage":
[]},
{"block":786383,"size":0,"storage":
[]},
{"block":786384,"size":0,"storage":
[]},
{"block":786385,"size":0,"storage":
[]},
{"block":786386,"size":0,"storage":
[]},
{"block":786387,"size":0,"storage":
[]},
{"block":786388,"size":0,"storage":
[]},
{"block":786389,"size":0,"storage":
[]},
{"block":786390,"size":0,"storage":
[]},
{"block":786391,"size":0,"storage":
[]},
{"block":786392,"size":0,"storage":
[]},
{"block":786393,"size":0,"storage":
[]},
{"block":786394,"size":0,"storage":
[]},
{"block":786395,"size":0,"storage":
[]},
{"block":786396,"size":0,"storage":
[]},
{"block":786397,"size":0,"storage":
[]},
{"block":786398,"size":0,"storage":
[]},
{"block":786399,"size":0,"storage":
[]},
{"block":786400,"size":0,"storage":
[]},
{"block":786401,"size":0,"storage":
[]},
{"block":786402,"size":0,"storage":
[]},
{"block":786403,"size":0,"storage":
[]},
{"block":786404,"size":0,"storage":
[]},
{"block":786405,"size":0,"storage":
[]},
{"block":786406,"size":0,"storage":
[]},
{"block":786407,"size":0,"storage":
[]},
{"block":786408,"size":0,"storage":
[]},
{"block":786409,"size":0,"storage":
[]},
{"block":786410,"size":0,"storage":
[]},
{"block":786411,"size":0,"storage":
[]},
{"block":786412,"size":0,"storage":
[]},
{"block":786413,"size":0,"storage":
[]},
{"block":786414,"size":0,"storage":
[]},
{"block":786415,"size":0,"storage":
[]},
{"block":786416,"size":0,"storage":
[]},
{"block":786417,"size":0,"storage":
[]},
{"block":786418,"size":0,"storage":
[]},
{"block":786419,"size":0,"storage":
[]},
{"block":786420,"size":0,"storage":
[]},
{"block":786421,"size":0,"storage":
[]},
{"block":786422,"size":0,"storage":
[]},
{"block":786423,"size":0,"storage":
[]},
{"block":786424,"size":0,"storage":
[]},
{"block":786425,"size":0,"storage":
[]},
{"block":786426,"size":0,"storage":
[]},
{"block":786427,"size":0,"storage":
[]},
{"block":786428,"size":0,"storage":
[]},
{"block":786429,"size":0,"storage":
[]},
{"block":786430,"size":0,"storage":
[]},
{"block":786431,"size":0,"storage":
[]},
{"block":786432,"size":0,"storage":
[]},
{"block":786433,"size":0,"storage":
[]},
{"block":786434,"size":0,"storage":
[]},
{"block":786435,"size":0,"storage":
[]},
{"block":786436,"size":0,"storage":
[]},
{"block":786437,"size":0,"storage":
[]},
{"block":786438,"size":0,"storage":
[]},
{"block":786439,"size":0,"storage":
[]},
{"block":786440,"size":0,"storage":
[]},
{"block":786441,"size":0,"storage":
[]},
{"block":786442,"size":0,"storage":
[]},
{"block":786443,"size":0,"storage":
[]},
{"block":786444,"size":0,"storage":
[]},
{"block":786445,"size":0,"storage":
[]},
{"block":786446,"size":0,"storage":
[]},
{"block":786447,"size":0,"storage":
[]},
{"block":786448,"size":0,"storage":
[]},
{"block":786449,"size":0,"storage":
[]},
{"block":786450,"size":0,"storage":
[]},
{"block":786451,"size":0,"storage":
[]},
{"block":786452,"size":0,"storage":
[]},
{"block":786453,"size":0,"storage":
[]},
{"block":786454,"size":0,"storage":
[]},
{"block":786455,"size":0,"storage":
[]},
{"block":786456,"size":0,"storage":
[]},
{"block":786457,"size":0,"storage":
[]},
{"block":786458,"size":0,"storage":
[]},
{"block":786459,"size":0,"storage":
[]},
{"block":786460,"size":0,"storage":
[]},
{"block":786461,"size":0,"storage":
[]},
{"block":786462,"size":0,"storage":
[]},
{"block":786463,"size":0,"storage":
[]},
{"block":786464,"size":0,"storage":
[]},
{"block":786465,"size":0,"storage":
[]},
{"block":786466,"size":0,"storage":
[]},
{"block":786467,"size":0,"storage":
[]},
{"block":786468,"size":0,"storage":
[]},
{"block":786469,"size":0,"storage":
[]},
{"block":786470,"size":0,"storage":
[]},
{"block":786471,"size":0,"storage":
[]},
{"block":786472,"size":0,"storage":
[]},
{"block":786473,"size":0,"storage":
[]},
{"block":786474,"size":0,"storage":
[]},
{"block":786475,"size":0,"storage":
[]},
{"block":786476,"size":0,"storage":
[]},
{"block":786477,"size":0,"storage":
[]},
{"block":786478,"size":0,"storage":
[]},
{"block":786479,"size":0,"storage":
[]},
{"block":786480,"size":0,"storage":
[]},
{"block":786481,"size":0,"storage":
[]},
{"block":786482,"size":0,"storage":
[]},
{"block":786483,"size":0,"storage":
[]},
{"block":786484,"size":0,"storage":
[]},
{"block":786485,"size":0,"storage":
[]},
{"block":786486,"size":0,"storage":
[]},
{"block":786487,"size":0,"storage":
[]},
{"block":786488,"size":0,"storage":
[]},
{"block":786489,"size":0,"storage":
[]},
{"block":786490,"size":0,"storage":
[]},
{"block":786491,"size":0,"storage":
[]},
{"block":786492,"size":0,"storage":
[]},
{"block":786493,"size":0,"storage":
[]},
{"block":786494,"size":0,"storage":
[]},
{"block":786495,"size":0,"storage":
[]},
{"block":786496,"size":0,"storage":
[]},
{"block":786497,"size":0,"storage":
[]},
{"block":786498,"size":0,"storage":
[]},
{"block":786499,"size":0,"storage":
[]},
{"block":786500,"size":0,"storage":
[]},
{"block":786501,"size":0,"storage":
[]},
{"block":786502,"size":0,"storage":
[]},
{"block":786503,"size":0,"storage":
[]},
{"block":786504,"size":0,"storage":
[]},
{"block":786505,"size":0,"storage":
[]},
{"block":786506,"size":0,"storage":
[]},
{"block":786507,"size":0,"storage":
[]},
{"block":786508,"size":0,"storage":
[]},
{"block":786509,"size":0,"storage":
[]},
{"block":786510,"size":0,"storage":
[]},
{"block":786511,"size":0,"storage":
[]},
{"block":786512,"size":0,"storage":
[]},
{"block":786513,"size":0,"storage":
[]},
{"block":786514,"size":0,"storage":
[]},
{"block":786515,"size":0,"storage":
[]},
{"block":786516,"size":0,"storage":
[]},
{"block":786517,"size":0,"storage":
[]},
{"block":786518,"size":0,"storage":
[]},
{"block":786519,"size":0,"storage":
[]},
{"block":786520,"size":0,"storage":
[]},
{"block":786521,"size":0,"storage":
[]},
{"block":786522,"size":0,"storage":
[]},
{"block":786523,"size":0,"storage":
[]},
{"block":786524,"size":0,"storage":
[]},
{"block":786525,"size":0,"storage":
[]},
{"block":786526,"size":0,"storage":
[]},
{"block":786527,"size":0,"storage":
[]},
{"block":786528,"size":0,"storage":
[]},
{"block":786529,"size":0,"storage":
[]},
{"block":786530,"size":0,"storage":
[]},
{"block":786531,"size":0,"storage":
[]},
{"block":786532,"size":0,"storage":
[]},
{"block":786533,"size":0,"storage":
[]},
{"block":786534,"size":0,"storage":
[]},
{"block":786535,"size":0,"storage":
[]},
{"block":786536,"size":0,"storage":
[]},
{"block":786537,"size":0,"storage":
[]},
{"block":786538,"size":0,"storage":
[]},
{"block":786539,"size":0,"storage":
[]},
{"block":786540,"size":0,"storage":
[]},
{"block":786541,"size":0,"storage":
[]},
{"block":786542,"size":0,"storage":
[]},
{"block":786543,"size":0,"storage":
[]},
{"block":786544,"size":0,"storage":
[]},
{"block":786545,"size":0,"storage":
[]},
{"block":786546,"size":0,"storage":
[]},
{"block":786547,"size":0,"storage":
[]},
{"block":786548,"size":0,"storage":
[]},
{"block":786549,"size":0,"storage":
[]},
{"block":786550,"size":0,"storage":
[]},
{"block":786551,"size":0,"storage":
[]},
{"block":786552,"size":0,"storage":
[]},
{"block":786553,"size":0,"storage":
[]},
{"block":786554,"size":0,"storage":
[]},
{"block":786555,"size":0,"storage":
[]},
{"block":786556,"size":0,"storage":
[]},
{"block":786557,"size":0,"storage":
[]},
{"block":786558,"size":0,"storage":
[]},
{"block":786559,"size":0,"storage":
[]},
{"block":786560,"size":0,"storage":
[]},
{"block":786561,"size":0,"storage":
[]},
{"block":786562,"size":0,"storage":
[]},
{"block":786563,"size":0,"storage":
[]},
{"block":786564,"size":0,"storage":
[]},
{"block":786565,"size":0,"storage":
[]},
{"block":786566,"size":0,"storage":
[]},
{"block":786567,"size":0,"storage":
[]},
{"block":786568,"size":0,"storage":
[]},
{"block":786569,"size":0,"storage":
[]},
{"block":786570,"size":0,"storage":
[]},
{"block":786571,"size":0,"storage":
[]},
{"block":786572,"size":0,"storage":
[]},
{"block":786573,"size":0,"storage":
[]},
{"block":786574,"size":0,"storage":
[]},
{"block":786575,"size":0,"storage":
[]},
{"block":786576,"size":0,"storage":
[]},
{"block":786577,"size":0,"storage":
[]},
{"block":786578,"size":0,"storage":
[]},
{"block":786579,"size":0,"storage":
[]},
{"block":786580,"size":0,"storage":
[]},
{"block":786581,"size":0,"storage":
[]},
{"block":786582,"size":0,"storage":
[]},
{"block":786583,"size":0,"storage":
[]},
{"block":786584,"size":0,"storage":
[]},
{"block":786585,"size":0,"storage":
[]},
{"block":786586,"size":0,"storage":
[]},
{"block":786587,"size":0,"storage":
[]},
{"block":786588,"size":0,"storage":
[]},
{"block":786589,"size":0,"storage":
[]},
{"block":786590,"size":0,"storage":
[]},
{"block":786591,"size":0,"storage":
[]},
{"block":786592,"size":0,"storage":
[]},
{"block":786593,"size":0,"storage":
[]},
{"block":786594,"size":0,"storage":
[]},
{"block":786595,"size":0,"storage":
[]},
{"block":786596,"size":0,"storage":
[]},
{"block":786597,"size":0,"storage":
[]},
{"block":786598,"size":0,"storage":
[]},
{"block":786599,"size":0,"storage":
[]},
{"block":786600,"size":0,"storage":
[]},
{"block":786601,"size":0,"storage":
[]},
{"block":786602,"size":0,"storage":
[]},
{"block":786603,"size":0,"storage":
[]},
{"block":786604,"size":0,"storage":
[]},
{"block":786605,"size":0,"storage":
[]},
{"block":786606,"size":0,"storage":
[]},
{"block":786607,"size":0,"storage":
[]},
{"block":786608,"size":0,"storage":
[]},
{"block":786609,"size":0,"storage":
[]},
{"block":786610,"size":0,"storage":
[]},
{"block":786611,"size":0,"storage":
[]},
{"block":786612,"size":0,"storage":
[]},
{"block":786613,"size":0,"storage":
[]},
{"block":786614,"size":0,"storage":
[]},
{"block":786615,"size":0,"storage":
[]},
{"block":786616,"size":0,"storage":
[]},
{"block":786617,"size":0,"storage":
[]},
{"block":786618,"size":0,"storage":
[]},
{"block":786619,"size":0,"storage":
[]},
{"block":786620,"size":0,"storage":
[]},
{"block":786621,"size":0,"storage":
[]},
{"block":786622,"size":0,"storage":
[]},
{"block":786623,"size":0,"storage":
[]},
{"block":786624,"size":0,"storage":
[]},
{"block":786625,"size":0,"storage":
[]},
{"block":786626,"size":0,"storage":
[]},
{"block":786627,"size":0,"storage":
[]},
{"block":786628,"size":0,"storage":
[]},
{"block":786629,"size":0,"storage":
[]},
{"block":786630,"size":0,"storage":
[]},
{"block":786631,"size":0,"storage":
[]},
{"block":786632,"size":0,"storage":
[]},
{"block":786633,"size":0,"storage":
[]},
{"block":786634,"size":0,"storage":
[]},
{"block":786635,"size":0,"storage":
[]},
{"block":786636,"size":0,"storage":
[]},
{"block":786637,"size":0,"storage":
[]},
{"block":786638,"size":0,"storage":
[]},
{"block":786639,"size":0,"storage":
[]},
{"block":786640,"size":0,"storage":
[]},
{"block":786641,"size":0,"storage":
[]},
{"block":786642,"size":0,"storage":
[]},
{"block":786643,"size":0,"storage":
[]},
{"block":786644,"size":0,"storage":
[]},
{"block":786645,"size":0,"storage":
[]},
{"block":786646,"size":0,"storage":
[]},
{"block":786647,"size":0,"storage":
[]},
{"block":786648,"size":0,"storage":
[]},
{"block":786649,"size":0,"storage":
[]},
{"block":786650,"size":0,"storage":
[]},
{"block":786651,"size":0,"storage":
[]},
{"block":786652,"size":0,"storage":
[]},
{"block":786653,"size":0,"storage":
[]},
{"block":786654,"size":0,"storage":
[]},
{"block":786655,"size":0,"storage":
[]},
{"block":786656,"size":0,"storage":
[]},
{"block":786657,"size":0,"storage":
[]},
{"block":786658,"size":0,"storage":
[]},
{"block":786659,"size":0,"storage":
[]},
{"block":786660,"size":0,"storage":
[]},
{"block":786661,"size":0,"storage":
[]},
{"block":786662,"size":0,"storage":
[]},
{"block":786663,"size":0,"storage":
[]},
{"block":786664,"size":0,"storage":
[]},
{"block":786665,"size":0,"storage":
[]},
{"block":786666,"size":0,"storage":
[]},
{"block":786667,"size":0,"storage":
[]},
{"block":786668,"size":0,"storage":
[]},
{"block":786669,"size":0,"storage":
[]},
{"block":786670,"size":0,"storage":
[]},
{"block":786671,"size":0,"storage":
[]},
{"block":786672,"size":0,"storage":
[]},
{"block":786673,"size":0,"storage":
[]},
{"block":786674,"size":0,"storage":
[]},
{"block":786675,"size":0,"storage":
[]},
{"block":786676,"size":0,"storage":
[]},
{"block":786677,"size":0,"storage":
[]},
{"block":786678,"size":0,"storage":
[]},
{"block":786679,"size":0,"storage":
[]},
{"block":786680,"size":0,"storage":
[]},
{"block":786681,"size":0,"storage":
[]},
{"block":786682,"size":0,"storage":
[]},
{"block":786683,"size":0,"storage":
[]},
{"block":786684,"size":0,"storage":
[]},
{"block":786685,"size":0,"storage":
[]},
{"block":786686,"size":0,"storage":
[]},
{"block":786687,"size":0,"storage":
[]},
{"block":786688,"size":0,"storage":
[]},
{"block":786689,"size":0,"storage":
[]},
{"block":786690,"size":0,"storage":
[]},
{"block":786691,"size":0,"storage":
[]},
{"block":786692,"size":0,"storage":
[]},
{"block":786693,"size":0,"storage":
[]},
{"block":786694,"size":0,"storage":
[]},
{"block":786695,"size":0,"storage":
[]},
{"block":786696,"size":0,"storage":
[]},
{"block":786697,"size":0,"storage":
[]},
{"block":786698,"size":0,"storage":
[]},
{"block":786699,"size":0,"storage":
[]},
{"block":786700,"size":0,"storage":
[]},
{"block":786701,"size":0,"storage":
[]},
{"block":786702,"size":0,"storage":
[]},
{"block":786703,"size":0,"storage":
[]},
{"block":786704,"size":0,"storage":
[]},
{"block":786705,"size":0,"storage":
[]},
{"block":786706,"size":0,"storage":
[]},
{"block":786707,"size":0,"storage":
[]},
{"block":786708,"size":0,"storage":
[]},
{"block":786709,"size":0,"storage":
[]},
{"block":786710,"size":0,"storage":
[]},
{"block":786711,"size":0,"storage":
[]},
{"block":786712,"size":0,"storage":
[]},
{"block":786713,"size":0,"storage":
[]},
{"block":786714,"size":0,"storage":
[]},
{"block":786715,"size":0,"storage":
[]},
{"block":786716,"size":0,"storage":
[]},
{"block":786717,"size":0,"storage":
[]},
{"block":786718,"size":0,"storage":
[]},
{"block":786719,"size":0,"storage":
[]},
{"block":786720,"size":0,"storage":
[]},
{"block":786721,"size":0,"storage":
[]},
{"block":786722,"size":0,"storage":
[]},
{"block":786723,"size":0,"storage":
[]},
{"block":786724,"size":0,"storage":
[]},
{"block":786725,"size":0,"storage":
[]},
{"block":786726,"size":0,"storage":
[]},
{"block":786727,"size":0,"storage":
[]},
{"block":786728,"size":0,"storage":
[]},
{"block":786729,"size":0,"storage":
[]},
{"block":786730,"size":0,"storage":
[]},
{"block":786731,"size":0,"storage":
[]},
{"block":786732,"size":0,"storage":
[]},
{"block":786733,"size":0,"storage":
[]},
{"block":786734,"size":0,"storage":
[]},
{"block":786735,"size":0,"storage":
[]},
{"block":786736,"size":0,"storage":
[]},
{"block":786737,"size":0,"storage":
[]},
{"block":786738,"size":0,"storage":
[]},
{"block":786739,"size":0,"storage":
[]},
{"block":786740,"size":0,"storage":
[]},
{"block":786741,"size":0,"storage":
[]},
{"block":786742,"size":0,"storage":
[]},
{"block":786743,"size":0,"storage":
[]},
{"block":786744,"size":0,"storage":
[]},
{"block":786745,"size":0,"storage":
[]},
{"block":786746,"size":0,"storage":
[]},
{"block":786747,"size":0,"storage":
[]},
{"block":786748,"size":0,"storage":
[]},
{"block":786749,"size":0,"storage":
[]},
{"block":786750,"size":0,"storage":
[]},
{"block":786751,"size":0,"storage":
[]},
{"block":786752,"size":0,"storage":
[]},
{"block":786753,"size":0,"storage":
[]},
{"block":786754,"size":0,"storage":
[]},
{"block":786755,"size":0,"storage":
[]},
{"block":786756,"size":0,"storage":
[]},
{"block":786757,"size":0,"storage":
[]},
{"block":786758,"size":0,"storage":
[]},
{"block":786759,"size":0,"storage":
[]},
{"block":786760,"size":0,"storage":
[]},
{"block":786761,"size":0,"storage":
[]},
{"block":786762,"size":0,"storage":
[]},
{"block":786763,"size":0,"storage":
[]},
{"block":786764,"size":0,"storage":
[]},
{"block":786765,"size":0,"storage":
[]},
{"block":786766,"size":0,"storage":
[]},
{"block":786767,"size":0,"storage":
[]},
{"block":786768,"size":0,"storage":
[]},
{"block":786769,"size":0,"storage":
[]},
{"block":786770,"size":0,"storage":
[]},
{"block":786771,"size":0,"storage":
[]},
{"block":786772,"size":0,"storage":
[]},
{"block":786773,"size":0,"storage":
[]},
{"block":786774,"size":0,"storage":
[]},
{"block":786775,"size":0,"storage":
[]},
{"block":786776,"size":0,"storage":
[]},
{"block":786777,"size":0,"storage":
[]},
{"block":786778,"size":0,"storage":
[]},
{"block":786779,"size":0,"storage":
[]},
{"block":786780,"size":0,"storage":
[]},
{"block":786781,"size":0,"storage":
[]},
{"block":786782,"size":0,"storage":
[]},
{"block":786783,"size":0,"storage":
[]},
{"block":786784,"size":0,"storage":
[]},
{"block":786785,"size":0,"storage":
[]},
{"block":786786,"size":0,"storage":
[]},
{"block":786787,"size":0,"storage":
[]},
{"block":786788,"size":0,"storage":
[]},
{"block":786789,"size":0,"storage":
[]},
{"block":786790,"size":0,"storage":
[]},
{"block":786791,"size":0,"storage":
[]},
{"block":786792,"size":0,"storage":
[]},
{"block":786793,"size":0,"storage":
[]},
{"block":786794,"size":0,"storage":
[]},
{"block":786795,"size":0,"storage":
[]},
{"block":786796,"size":0,"storage":
[]},
{"block":786797,"size":0,"storage":
[]},
{"block":786798,"size":0,"storage":
[]},
{"block":786799,"size":0,"storage":
[]},
{"block":786800,"size":0,"storage":
[]},
{"block":786801,"size":0,"storage":
[]},
{"block":786802,"size":0,"storage":
[]},
{"block":786803,"size":0,"storage":
[]},
{"block":786804,"size":0,"storage":
[]},
{"block":786805,"size":0,"storage":
[]},
{"block":786806,"size":0,"storage":
[]},
{"block":786807,"size":0,"storage":
[]},
{"block":786808,"size":0,"storage":
[]},
{"block":786809,"size":0,"storage":
[]},
{"block":786810,"size":0,"storage":
[]},
{"block":786811,"size":0,"storage":
[]},
{"block":786812,"size":0,"storage":
[]},
{"block":786813,"size":0,"storage":
[]},
{"block":786814,"size":0,"storage":
[]},
{"block":786815,"size":0,"storage":
[]},
{"block":786816,"size":0,"storage":
[]},
{"block":786817,"size":0,"storage":
[]},
{"block":786818,"size":0,"storage":
[]},
{"block":786819,"size":0,"storage":
[]},
{"block":786820,"size":0,"storage":
[]},
{"block":786821,"size":0,"storage":
[]},
{"block":786822,"size":0,"storage":
[]},
{"block":786823,"size":0,"storage":
[]},
{"block":786824,"size":0,"storage":
[]},
{"block":786825,"size":0,"storage":
[]},
{"block":786826,"size":0,"storage":
[]},
{"block":786827,"size":0,"storage":
[]},
{"block":786828,"size":0,"storage":
[]},
{"block":786829,"size":0,"storage":
[]},
{"block":786830,"size":0,"storage":
[]},
{"block":786831,"size":0,"storage":
[]},
{"block":786832,"size":0,"storage":
[]},
{"block":786833,"size":0,"storage":
[]},
{"block":786834,"size":0,"storage":
[]},
{"block":786835,"size":0,"storage":
[]},
{"block":786836,"size":0,"storage":
[]},
{"block":786837,"size":0,"storage":
[]},
{"block":786838,"size":0,"storage":
[]},
{"block":786839,"size":0,"storage":
[]},
{"block":786840,"size":0,"storage":
[]},
{"block":786841,"size":0,"storage":
[]},
{"block":786842,"size":0,"storage":
[]},
{"block":786843,"size":0,"storage":
[]},
{"block":786844,"size":0,"storage":
[]},
{"block":786845,"size":0,"storage":
[]},
{"block":786846,"size":0,"storage":
[]},
{"block":786847,"size":0,"storage":
[]},
{"block":786848,"size":0,"storage":
[]},
{"block":786849,"size":0,"storage":
[]},
{"block":786850,"size":0,"storage":
[]},
{"block":786851,"size":0,"storage":
[]},
{"block":786852,"size":0,"storage":
[]},
{"block":786853,"size":0,"storage":
[]},
{"block":786854,"size":0,"storage":
[]},
{"block":786855,"size":0,"storage":
[]},
{"block":786856,"size":0,"storage":
[]},
{"block":786857,"size":0,"storage":
[]},
{"block":786858,"size":0,"storage":
[]},
{"block":786859,"size":0,"storage":
[]},
{"block":786860,"size":0,"storage":
[]},
{"block":786861,"size":0,"storage":
[]},
{"block":786862,"size":0,"storage":
[]},
{"block":786863,"size":0,"storage":
[]},
{"block":786864,"size":0,"storage":
[]},
{"block":786865,"size":0,"storage":
[]},
{"block":786866,"size":0,"storage":
[]},
{"block":786867,"size":0,"storage":
[]},
{"block":786868,"size":0,"storage":
[]},
{"block":786869,"size":0,"storage":
[]},
{"block":786870,"size":0,"storage":
[]},
{"block":786871,"size":0,"storage":
[]},
{"block":786872,"size":0,"storage":
[]},
{"block":786873,"size":0,"storage":
[]},
{"block":786874,"size":0,"storage":
[]},
{"block":786875,"size":0,"storage":
[]},
{"block":786876,"size":0,"storage":
[]},
{"block":786877,"size":0,"storage":
[]},
{"block":786878,"size":0,"storage":
[]},
{"block":786879,"size":0,"storage":
[]},
{"block":786880,"size":0,"storage":
[]},
{"block":786881,"size":0,"storage":
[]},
{"block":786882,"size":0,"storage":
[]},
{"block":786883,"size":0,"storage":
[]},
{"block":786884,"size":0,"storage":
[]},
{"block":786885,"size":0,"storage":
[]},
{"block":786886,"size":0,"storage":
[]},
{"block":786887,"size":0,"storage":
[]},
{"block":786888,"size":0,"storage":
[]},
{"block":786889,"size":0,"storage":
[]},
{"block":786890,"size":0,"storage":
[]},
{"block":786891,"size":0,"storage":
[]},
{"block":786892,"size":0,"storage":
[]},
{"block":786893,"size":0,"storage":
[]},
{"block":786894,"size":0,"storage":
[]},
{"block":786895,"size":0,"storage":
[]},
{"block":786896,"size":0,"storage":
[]},
{"block":786897,"size":0,"storage":
[]},
{"block":786898,"size":0,"storage":
[]},
{"block":786899,"size":0,"storage":
[]},
{"block":786900,"size":0,"storage":
[]},
{"block":786901,"size":0,"storage":
[]},
{"block":786902,"size":0,"storage":
[]},
{"block":786903,"size":0,"storage":
[]},
{"block":786904,"size":0,"storage":
[]},
{"block":786905,"size":0,"storage":
[]},
{"block":786906,"size":0,"storage":
[]},
{"block":786907,"size":0,"storage":
[]},
{"block":786908,"size":0,"storage":
[]},
{"block":786909,"size":0,"storage":
[]},
{"block":786910,"size":0,"storage":
[]},
{"block":786911,"size":0,"storage":
[]},
{"block":786912,"size":0,"storage":
[]},
{"block":786913,"size":0,"storage":
[]},
{"block":786914,"size":0,"storage":
[]},
{"block":786915,"size":0,"storage":
[]},
{"block":786916,"size":0,"storage":
[]},
{"block":786917,"size":0,"storage":
[]},
{"block":786918,"size":0,"storage":
[]},
{"block":786919,"size":0,"storage":
[]},
{"block":786920,"size":0,"storage":
[]},
{"block":786921,"size":0,"storage":
[]},
{"block":786922,"size":0,"storage":
[]},
{"block":786923,"size":0,"storage":
[]},
{"block":786924,"size":0,"storage":
[]},
{"block":786925,"size":0,"storage":
[]},
{"block":786926,"size":0,"storage":
[]},
{"block":786927,"size":0,"storage":
[]},
{"block":786928,"size":0,"storage":
[]},
{"block":786929,"size":0,"storage":
[]},
{"block":786930,"size":0,"storage":
[]},
{"block":786931,"size":0,"storage":
[]},
{"block":786932,"size":0,"storage":
[]},
{"block":786933,"size":0,"storage":
[]},
{"block":786934,"size":0,"storage":
[]},
{"block":786935,"size":0,"storage":
[]},
{"block":786936,"size":0,"storage":
[]},
{"block":786937,"size":0,"storage":
[]},
{"block":786938,"size":0,"storage":
[]},
{"block":786939,"size":0,"storage":
[]},
{"block":786940,"size":0,"storage":
[]},
{"block":786941,"size":0,"storage":
[]},
{"block":786942,"size":0,"storage":
[]},
{"block":786943,"size":0,"storage":
[]},
{"block":786944,"size":0,"storage":
[]},
{"block":786945,"size":0,"storage":
[]},
{"block":786946,"size":0,"storage":
[]},
{"block":786947,"size":0,"storage":
[]},
{"block":786948,"size":0,"storage":
[]},
{"block":786949,"size":0,"storage":
[]},
{"block":786950,"size":0,"storage":
[]},
{"block":786951,"size":0,"storage":
[]},
{"block":786952,"size":0,"storage":
[]},
{"block":786953,"size":0,"storage":
[]},
{"block":786954,"size":0,"storage":
[]},
{"block":786955,"size":0,"storage":
[]},
{"block":786956,"size":0,"storage":
[]},
{"block":786957,"size":0,"storage":
[]},
{"block":786958,"size":0,"storage":
[]},
{"block":786959,"size":0,"storage":
[]},
{"block":786960,"size":0,"storage":
[]},
{"block":786961,"size":0,"storage":
[]},
{"block":786962,"size":0,"storage":
[]},
{"block":786963,"size":0,"storage":
[]},
{"block":786964,"size":0,"storage":
[]},
{"block":786965,"size":0,"storage":
[]},
{"block":786966,"size":0,"storage":
[]},
{"block":786967,"size":0,"storage":
[]},
{"block":786968,"size":0,"storage":
[]},
{"block":786969,"size":0,"storage":
[]},
{"block":786970,"size":0,"storage":
[]},
{"block":786971,"size":0,"storage":
[]},
{"block":786972,"size":0,"storage":
[]},
{"block":786973,"size":0,"storage":
[]},
{"block":786974,"size":0,"storage":
[]},
{"block":786975,"size":0,"storage":
[]},
{"block":786976,"size":0,"storage":
[]},
{"block":786977,"size":0,"storage":
[]},
{"block":786978,"size":0,"storage":
[]},
{"block":786979,"size":0,"storage":
[]},
{"block":786980,"size":0,"storage":
[]},
{"block":786981,"size":0,"storage":
[]},
{"block":786982,"size":0,"storage":
[]},
{"block":786983,"size":0,"storage":
[]},
{"block":786984,"size":0,"storage":
[]},
{"block":786985,"size":0,"storage":
[]},
{"block":786986,"size":0,"storage":
[]},
{"block":786987,"size":0,"storage":
[]},
{"block":786988,"size":0,"storage":
[]},
{"block":786989,"size":0,"storage":
[]},
{"block":786990,"size":0,"storage":
[]},
{"block":786991,"size":0,"storage":
[]},
{"block":786992,"size":0,"storage":
[]},
{"block":786993,"size":0,"storage":
[]},
{"block":786994,"size":0,"storage":
[]},
{"block":786995,"size":0,"storage":
[]},
{"block":786996,"size":0,"storage":
[]},
{"block":786997,"size":0,"storage":
[]},
{"block":786998,"size":0,"storage":
[]},
{"block":786999,"size":0,"storage":
[]},
{"block":787000,"size":0,"storage":
[]},
]